lab4/HW04_HanJoo/GLOBAL.v
`define		ALU_ADDU			4'b0000
`define		ALU_AND				4'b0001
`define		ALU_NOR				4'b0010
`define		ALU_OR				4'b0011
`define		ALU_SLL				4'b0100
`define		ALU_SRA				4'b0101
`define		ALU_SRL				4'b0110
`define		ALU_SUBU			4'b0111
`define		ALU_XOR				4'b1000
`define		ALU_SLT				4'b1001
`define		ALU_SLTU			4'b1010
`define		ALU_EQ				4'b1011
`define		ALU_NEQ				4'b1100
`define		ALU_LUI				4'b1101

`define		FUNCT_SLL			6'd0
`define		FUNCT_SRL			6'd2
`define		FUNCT_SRA			6'd3
`define 	FUNCT_JR			6'd8
`define		FUNCT_ADDU		6'd33
`define		FUNCT_SUBU		6'd35
`define		FUNCT_AND			6'd36
`define		FUNCT_OR			6'd37
`define		FUNCT_XOR			6'd38
`define		FUNCT_NOR			6'd39
`define		FUNCT_SLT			6'd42
`define		FUNCT_SLTU		6'd43

`define		OP_RTYPE			6'd0
`define		OP_J				  6'd2
`define		OP_JAL				6'd3
`define		OP_BEQ				6'd4
`define		OP_BNE				6'd5
`define		OP_ADDIU			6'd9
`define		OP_SLTI				6'd10
`define		OP_SLTIU			6'd11
`define		OP_ANDI				6'd12
`define		OP_ORI				6'd13
`define		OP_XORI				6'd14
`define		OP_LUI				6'd15
`define		OP_LW			  	6'd35
`define		OP_SW				  6'd43

`define   STATE_IF      3'd0
`define   STATE_ID      3'd1
`define   STATE_EX      3'd2
`define   STATE_MEM     3'd3
`define   STATE_WB      3'd4

lab1/HW01 Skeleton Code/ALU.v
`timescale 1ns / 1ps
`include "GLOBAL.v"

// this is a combinational logic
module ALU(
		input [31:0]		operand1,
		input [31:0]		operand2,
		input [4:0]			shamt,
		input [3:0]			funct,
		output reg [31:0]	alu_result
	);
	
	// FIXME
	always @(*) begin
		alu_result = 0;
		case (funct)
			`ALU_ADDU:
			`ALU_AND :
			`ALU_NOR :
			`ALU_OR  :
			`ALU_SLL :
			`ALU_SRA :
			`ALU_SRL :
			`ALU_SUBU:
			`ALU_XOR :
			`ALU_SLT :
			`ALU_SLTU:
			`ALU_EQ  :
			`ALU_NEQ :
			`ALU_LUI :
		endcase
	end
endmodule

lab1/HW01/ALU_tb.v
`timescale 1ns / 100ps

module ALU_tb;
	// FIXME (Set the number of tests)
	// Depending on the number of testcases you generate in the CPP code
	parameter TEST_SIZE = 10000;

	reg [31:0] operand1;
	reg [31:0] operand2;
	reg [4:0] shamt;
	reg [3:0] funct;
	
	wire [31:0] alu_result;

	reg [31:0] operand1_mem [0:TEST_SIZE-1];
	reg [31:0] operand2_mem [0:TEST_SIZE-1];
	reg [4:0]  shamt_mem [0:TEST_SIZE-1];
	reg [3:0]  funct_mem [0:TEST_SIZE-1];
	reg [31:0] alu_result_mem [0:TEST_SIZE-1];

	integer PASSED;
	integer FAILED;
	integer i;
	
	ALU alu_top (.operand1(operand1), .operand2(operand2),
				.shamt(shamt), .funct(funct), .alu_result(alu_result));
	
	task Test; 
		input [31:0] operand1_in;
		input [31:0] operand2_in;
		input [4:0] shamt_in;
		input [3:0] funct_in;
		input [31:0] alu_result_in;
	begin  
		operand1 = operand1_in;
		operand2 = operand2_in;
		shamt = shamt_in;
		funct = funct_in;
		// $display("TEST CTRL Sig: %h :", funct);
		#1;
		if (alu_result == alu_result_in) begin
			// $display("PASSED");
			PASSED = PASSED + 1;
		end
		else begin
			$display("FAILED");
			$display("funct: %d, operand1 = %d, operand2 = %d, shamt = %d, result = %h (Ans : %h)",
						funct, operand1, operand2, shamt, alu_result, alu_result_in);
			FAILED = FAILED + 1;
		end	
	end
	endtask

	// Load the data from the memory
	initial begin
		$readmemh("operand1.mem", operand1_mem);
		$readmemh("operand2.mem", operand2_mem);
		$readmemb("shamt.mem", shamt_mem);
		$readmemb("funct.mem", funct_mem);
		$readmemh("alu_result.mem", alu_result_mem);
	end
	
	initial begin
        $dumpfile("waveform.vcd");
        $dumpvars(0,ALU_tb);
    end

	initial begin
		i = 0;
		PASSED = 0;
		FAILED = 0;
		#10
		
		for (i = 0; i < TEST_SIZE; i = i + 1) begin
			Test(operand1_mem[i], operand2_mem[i], shamt_mem[i], funct_mem[i], alu_result_mem[i]);
		end
		
		#10
		$display("PASSED = %d, FAILED = %d", PASSED, FAILED);
		$finish;
	end
endmodule

lab1/HW01/waveform.vcd
$date
	Sat Mar 28 17:02:06 2026
$end
$version
	Icarus Verilog
$end
$timescale
	1ps
$end
$scope module ALU_tb $end
$var wire 32 ! alu_result [31:0] $end
$var parameter 32 " TEST_SIZE $end
$var reg 4 # funct [3:0] $end
$var reg 32 $ operand1 [31:0] $end
$var reg 32 % operand2 [31:0] $end
$var reg 5 & shamt [4:0] $end
$var integer 32 ' FAILED [31:0] $end
$var integer 32 ( PASSED [31:0] $end
$var integer 32 ) i [31:0] $end
$scope module alu_top $end
$var wire 4 * funct [3:0] $end
$var wire 32 + operand1 [31:0] $end
$var wire 32 , operand2 [31:0] $end
$var wire 5 - shamt [4:0] $end
$var reg 32 . alu_result [31:0] $end
$upscope $end
$scope task Test $end
$var reg 32 / alu_result_in [31:0] $end
$var reg 4 0 funct_in [3:0] $end
$var reg 32 1 operand1_in [31:0] $end
$var reg 32 2 operand2_in [31:0] $end
$var reg 5 3 shamt_in [4:0] $end
$upscope $end
$upscope $end
$enddefinitions $end
$comment Show the parameter values. $end
$dumpall
b10011100010000 "
$end
#0
$dumpvars
bx 3
bx 2
bx 1
bx 0
bx /
bx .
bx -
bx ,
bx +
bx *
b0 )
b0 (
b0 '
bx &
bx %
bx $
bx #
bx !
$end
#10000
b101111101111011111111111010101 !
b101111101111011111111111010101 .
b11 #
b11 *
b10001 &
b10001 -
b101110101011000111100101000101 %
b101110101011000111100101000101 ,
b1001100100011010111010010100 $
b1001100100011010111010010100 +
b101111101111011111111111010101 /
b11 0
b10001 3
b101110101011000111100101000101 2
b1001100100011010111010010100 1
#11000
b11111111111111111111111111100011 !
b11111111111111111111111111100011 .
b101 #
b101 *
b11010 &
b11010 -
b10001110000001001011101100011111 %
b10001110000001001011101100011111 ,
b10111000001001101000000110000000 $
b10111000001001101000000110000000 +
b11111111111111111111111111100011 /
b101 0
b11010 3
b10001110000001001011101100011111 2
b10111000001001101000000110000000 1
b1 )
b1 (
#12000
b11110110000100101001011111010011 !
b11110110000100101001011111010011 .
b1000 #
b1000 *
b11100 &
b11100 -
b1101001000010110011010100001100 %
b1101001000010110011010100001100 ,
b10011111000110011010001011011111 $
b10011111000110011010001011011111 +
b11110110000100101001011111010011 /
b1000 0
b11100 3
b1101001000010110011010100001100 2
b10011111000110011010001011011111 1
b10 )
b10 (
#13000
b0 !
b0 .
b1001 #
b1001 *
b111 &
b111 -
b100011010000110011000000011110 %
b100011010000110011000000011110 ,
b1110001111100010011100010100000 $
b1110001111100010011100010100000 +
b0 /
b1001 0
b111 3
b100011010000110011000000011110 2
b1110001111100010011100010100000 1
b11 )
b11 (
#14000
b10111100100 !
b10111100100 .
b101 #
b101 *
b10011 &
b10011 -
b101111001001110110010010111111 %
b101111001001110110010010111111 ,
b1011011011011100100010001000110 $
b1011011011011100100010001000110 +
b10111100100 /
b101 0
b10011 3
b101111001001110110010010111111 2
b1011011011011100100010001000110 1
b100 )
b100 (
#15000
b0 !
b0 .
b1001 #
b1001 *
b1101 &
b1101 -
b11000010101110100101001111111110 %
b11000010101110100101001111111110 ,
b11101110101101111001000100101100 $
b11101110101101111001000100101100 +
b0 /
b1001 0
b1101 3
b11000010101110100101001111111110 2
b11101110101101111001000100101100 1
b101 )
b101 (
#16000
b1011 #
b1011 *
b101 &
b101 -
b10101101100111100011101010100000 %
b10101101100111100011101010100000 ,
b11111010110111110101100010111010 $
b11111010110111110101100010111010 +
b1011 0
b101 3
b10101101100111100011101010100000 2
b11111010110111110101100010111010 1
b110 )
b110 (
#17000
b10010010000101000001000110 !
b10010010000101000001000110 .
b10 #
b10 *
b11110 &
b11110 -
b1110101101001001010101110011001 %
b1110101101001001010101110011001 ,
b11011000100100110000010100100001 $
b11011000100100110000010100100001 +
b10010010000101000001000110 /
b10 0
b11110 3
b1110101101001001010101110011001 2
b11011000100100110000010100100001 1
b111 )
b111 (
#18000
b11010111101001000101001101000 !
b11010111101001000101001101000 .
b1000 #
b1000 *
b11011 &
b11011 -
b10010001101010111000001001100000 %
b10010001101010111000001001100000 ,
b10001011010111110000100000001000 $
b10001011010111110000100000001000 +
b11010111101001000101001101000 /
b1000 0
b11011 3
b10010001101010111000001001100000 2
b10001011010111110000100000001000 1
b1000 )
b1000 (
#19000
b10010111111111110111110111111 !
b10010111111111110111110111111 .
b11 #
b11 *
b10100 &
b10100 -
b10010111111011010010110011110 %
b10010111111011010010110011110 ,
b10000100011101100111010111001 $
b10000100011101100111010111001 +
b10010111111111110111110111111 /
b11 0
b10100 3
b10010111111011010010110011110 2
b10000100011101100111010111001 1
b1001 )
b1001 (
#20000
b101001111100010 !
b101001111100010 .
b101 #
b101 *
b10000 &
b10000 -
b1010011111000100000110000111111 %
b1010011111000100000110000111111 ,
b10111001001111011010011101111111 $
b10111001001111011010011101111111 +
b101001111100010 /
b101 0
b10000 3
b1010011111000100000110000111111 2
b10111001001111011010011101111111 1
b1010 )
b1010 (
#21000
b11011001111111010111110101111111 !
b11011001111111010111110101111111 .
b11 #
b11 *
b11100 &
b11100 -
b11011000101011010111110101100011 %
b11011000101011010111110101100011 ,
b11000001010111010110010100011101 $
b11000001010111010110010100011101 +
b11011001111111010111110101111111 /
b11 0
b11100 3
b11011000101011010111110101100011 2
b11000001010111010110010100011101 1
b1011 )
b1011 (
#22000
b110001111000010001101100010000 !
b110001111000010001101100010000 .
b0 #
b0 *
b1010 &
b1010 -
b1001010100100011011011110010011 %
b1001010100100011011011110010011 ,
b11100111010011110110001101111101 $
b11100111010011110110001101111101 +
b110001111000010001101100010000 /
b0 0
b1010 3
b1001010100100011011011110010011 2
b11100111010011110110001101111101 1
b1100 )
b1100 (
#23000
b10010110011111010111000111000010 !
b10010110011111010111000111000010 .
b11100 &
b11100 -
b11000101010101100101001101010110 %
b11000101010101100101001101010110 ,
b11010001001001110001111001101100 $
b11010001001001110001111001101100 +
b10010110011111010111000111000010 /
b11100 3
b11000101010101100101001101010110 2
b11010001001001110001111001101100 1
b1101 )
b1101 (
#24000
b10101100100001110000001000000000 !
b10101100100001110000001000000000 .
b1 #
b1 *
b10010 &
b10010 -
b10101100111101111010111101110001 %
b10101100111101111010111101110001 ,
b11111110100011110000001010001000 $
b11111110100011110000001010001000 +
b10101100100001110000001000000000 /
b1 0
b10010 3
b10101100111101111010111101110001 2
b11111110100011110000001010001000 1
b1110 )
b1110 (
#25000
b1010110000111011000011100111100 !
b1010110000111011000011100111100 .
b1000 #
b1000 *
b11011 &
b11011 -
b10110001011100010111011110000 %
b10110001011100010111011110000 ,
b1000000001100111010100111001100 $
b1000000001100111010100111001100 +
b1010110000111011000011100111100 /
b1000 0
b11011 3
b10110001011100010111011110000 2
b1000000001100111010100111001100 1
b1111 )
b1111 (
#26000
b11110010000011011110011101011101 !
b11110010000011011110011101011101 .
b0 #
b0 *
b100011110000111010110100111111 %
b100011110000111010110100111111 ,
b11001110010010100011101000011110 $
b11001110010010100011101000011110 +
b11110010000011011110011101011101 /
b0 0
b100011110000111010110100111111 2
b11001110010010100011101000011110 1
b10000 )
b10000 (
#27000
b100101101001001 !
b100101101001001 .
b110 #
b110 *
b10001 &
b10001 -
b10010110100100111011000100011111 %
b10010110100100111011000100011111 ,
b1101001000010101000000010001110 $
b1101001000010101000000010001110 +
b100101101001001 /
b110 0
b10001 3
b10010110100100111011000100011111 2
b1101001000010101000000010001110 1
b10001 )
b10001 (
#28000
b1101011010000100100000110001 !
b1101011010000100100000110001 .
b10 #
b10 *
b10101 &
b10101 -
b11110000100100100011011010001100 %
b11110000100100100011011010001100 ,
b11000010100101111010000101000110 $
b11000010100101111010000101000110 +
b1101011010000100100000110001 /
b10 0
b10101 3
b11110000100100100011011010001100 2
b11000010100101111010000101000110 1
b10010 )
b10010 (
#29000
b1000011010000010000001100001001 !
b1000011010000010000001100001001 .
b1 #
b1 *
b11100 &
b11100 -
b11000011110000110000001100001011 %
b11000011110000110000001100001011 ,
b1010011010111011101001111011101 $
b1010011010111011101001111011101 +
b1000011010000010000001100001001 /
b1 0
b11100 3
b11000011110000110000001100001011 2
b1010011010111011101001111011101 1
b10011 )
b10011 (
#30000
b0 !
b0 .
b1011 #
b1011 *
b10001 &
b10001 -
b11100000001011001010110010110011 %
b11100000001011001010110010110011 ,
b101010100011001010100111101001 $
b101010100011001010100111101001 +
b0 /
b1011 0
b10001 3
b11100000001011001010110010110011 2
b101010100011001010100111101001 1
b10100 )
b10100 (
#31000
b1 !
b1 .
b1010 #
b1010 *
b10111 &
b10111 -
b11101111001000010101100111111001 %
b11101111001000010101100111111001 ,
b11100000010001000001101010010101 $
b11100000010001000001101010010101 +
b1 /
b1010 0
b10111 3
b11101111001000010101100111111001 2
b11100000010001000001101010010101 1
b10101 )
b10101 (
#32000
b10000100101010000000010001010001 !
b10000100101010000000010001010001 .
b1 #
b1 *
b1010 &
b1010 -
b10000100101110100000111101011001 %
b10000100101110100000111101011001 ,
b10110100111010011111010001110011 $
b10110100111010011111010001110011 +
b10000100101010000000010001010001 /
b1 0
b1010 3
b10000100101110100000111101011001 2
b10110100111010011111010001110011 1
b10110 )
b10110 (
#33000
b0 !
b0 .
b1011 #
b1011 *
b100 &
b100 -
b10001100101100010110010011010111 %
b10001100101100010110010011010111 ,
b10001001011000010001010101100110 $
b10001001011000010001010101100110 +
b0 /
b1011 0
b100 3
b10001100101100010110010011010111 2
b10001001011000010001010101100110 1
b10111 )
b10111 (
#34000
b1101011110101101001110111100101 !
b1101011110101101001110111100101 .
b11 #
b11 *
b11100 &
b11100 -
b101010000001000001110011100100 %
b101010000001000001110011100100 ,
b1001011110101101000000101100001 $
b1001011110101101000000101100001 +
b1101011110101101001110111100101 /
b11 0
b11100 3
b101010000001000001110011100100 2
b1001011110101101000000101100001 1
b11000 )
b11000 (
#35000
b1010 !
b1010 .
b101 #
b101 *
b11010 &
b11010 -
b101001001100101101000110011011 %
b101001001100101101000110011011 ,
b100111100101000100010001101 $
b100111100101000100010001101 +
b1010 /
b101 0
b11010 3
b101001001100101101000110011011 2
b100111100101000100010001101 1
b11001 )
b11001 (
#36000
b11110011000111010101000001010010 !
b11110011000111010101000001010010 .
b1000 #
b1000 *
b11011 &
b11011 -
b11011111000010101101011001010101 %
b11011111000010101101011001010101 ,
b101100000101111000011000000111 $
b101100000101111000011000000111 +
b11110011000111010101000001010010 /
b1000 0
b11011 3
b11011111000010101101011001010101 2
b101100000101111000011000000111 1
b11010 )
b11010 (
#37000
b11010001001110000010 !
b11010001001110000010 .
b110 #
b110 *
b1001 &
b1001 -
b11010001001110000010011000000 %
b11010001001110000010011000000 ,
b100001011111101110001011101100 $
b100001011111101110001011101100 +
b11010001001110000010 /
b110 0
b1001 3
b11010001001110000010011000000 2
b100001011111101110001011101100 1
b11011 )
b11011 (
#38000
b11101110010001101101100001100010 !
b11101110010001101101100001100010 .
b1000 #
b1000 *
b11011 &
b11011 -
b11101000000111011100010101001010 %
b11101000000111011100010101001010 ,
b110010110110001110100101000 $
b110010110110001110100101000 +
b11101110010001101101100001100010 /
b1000 0
b11011 3
b11101000000111011100010101001010 2
b110010110110001110100101000 1
b11100 )
b11100 (
#39000
b1011000001011010010111001100 !
b1011000001011010010111001100 .
b0 #
b0 *
b11 &
b11 -
b1011011111001011110010000110011 %
b1011011111001011110010000110011 ,
b10101111000111111100000110011001 $
b10101111000111111100000110011001 +
b1011000001011010010111001100 /
b0 0
b11 3
b1011011111001011110010000110011 2
b10101111000111111100000110011001 1
b11101 )
b11101 (
#40000
b1 !
b1 .
b1001 #
b1001 *
b11011 &
b11011 -
b11001110010000111000011110000110 %
b11001110010000111000011110000110 ,
b10100010101001011000000011010111 $
b10100010101001011000000011010111 +
b1 /
b1001 0
b11011 3
b11001110010000111000011110000110 2
b10100010101001011000000011010111 1
b11110 )
b11110 (
#41000
b0 !
b0 .
b1011 #
b1011 *
b11101 &
b11101 -
b11001100111001111010000100001111 %
b11001100111001111010000100001111 ,
b11101000110100100000100101011101 $
b11101000110100100000100101011101 +
b0 /
b1011 0
b11101 3
b11001100111001111010000100001111 2
b11101000110100100000100101011101 1
b11111 )
b11111 (
#42000
b1101111111110011101110111110111 !
b1101111111110011101110111110111 .
b11 #
b11 *
b11111 &
b11111 -
b1101000110010010101100101010000 %
b1101000110010010101100101010000 ,
b1111111100001000110011110111 $
b1111111100001000110011110111 +
b1101111111110011101110111110111 /
b11 0
b11111 3
b1101000110010010101100101010000 2
b1111111100001000110011110111 1
b100000 )
b100000 (
#43000
b1 !
b1 .
b1001 #
b1001 *
b11011 &
b11011 -
b1011001111100010110011010010100 %
b1011001111100010110011010010100 ,
b1001001111011100010011000011001 $
b1001001111011100010011000011001 +
b1 /
b1001 0
b11011 3
b1011001111100010110011010010100 2
b1001001111011100010011000011001 1
b100001 )
b100001 (
#44000
b1100000000000100101001011 !
b1100000000000100101001011 .
b10 #
b10 *
b11000 &
b11000 -
b10010100001101111010001010000100 %
b10010100001101111010001010000100 ,
b11101010010111101101011000110100 $
b11101010010111101101011000110100 +
b1100000000000100101001011 /
b10 0
b11000 3
b10010100001101111010001010000100 2
b11101010010111101101011000110100 1
b100010 )
b100010 (
#45000
b101 !
b101 .
b110 #
b110 *
b11101 &
b11101 -
b10111110011110011111000100111111 %
b10111110011110011111000100111111 ,
b11000110000100110001101101010000 $
b11000110000100110001101101010000 +
b101 /
b110 0
b11101 3
b10111110011110011111000100111111 2
b11000110000100110001101101010000 1
b100011 )
b100011 (
#46000
b10111001000100110000000000000000 !
b10111001000100110000000000000000 .
b1101 #
b1101 *
b11010 &
b11010 -
b1100100000001001011100100010011 %
b1100100000001001011100100010011 ,
b1110001110010100010100111010111 $
b1110001110010100010100111010111 +
b10111001000100110000000000000000 /
b1101 0
b11010 3
b1100100000001001011100100010011 2
b1110001110010100010100111010111 1
b100100 )
b100100 (
#47000
b0 !
b0 .
b1001 #
b1001 *
b1 &
b1 -
b10001101100101111010100111011110 %
b10001101100101111010100111011110 ,
b11111111000101010100110111011101 $
b11111111000101010100110111011101 +
b0 /
b1001 0
b1 3
b10001101100101111010100111011110 2
b11111111000101010100110111011101 1
b100101 )
b100101 (
#48000
b110 #
b110 *
b11110 &
b11110 -
b101011011101100111111101001100 %
b101011011101100111111101001100 ,
b11000100100010110111110001101110 $
b11000100100010110111110001101110 +
b110 0
b11110 3
b101011011101100111111101001100 2
b11000100100010110111110001101110 1
b100110 )
b100110 (
#49000
b1001 #
b1001 *
b11100 &
b11100 -
b10100100111010010011011101111010 %
b10100100111010010011011101111010 ,
b1101111101001100010011011011101 $
b1101111101001100010011011011101 +
b1001 0
b11100 3
b10100100111010010011011101111010 2
b1101111101001100010011011011101 1
b100111 )
b100111 (
#50000
b1001000110101011010000000010101 !
b1001000110101011010000000010101 .
b1000 #
b1000 *
b10 &
b10 -
b10100010011010001110111100010101 %
b10100010011010001110111100010101 ,
b11101010101111010100111100000000 $
b11101010101111010100111100000000 +
b1001000110101011010000000010101 /
b1000 0
b10 3
b10100010011010001110111100010101 2
b11101010101111010100111100000000 1
b101000 )
b101000 (
#51000
b10000000000000001101000001000000 !
b10000000000000001101000001000000 .
b1 #
b1 *
b10101 &
b10101 -
b11000011000100001101010111010000 %
b11000011000100001101010111010000 ,
b10100100011010101101001001100110 $
b10100100011010101101001001100110 +
b10000000000000001101000001000000 /
b1 0
b10101 3
b11000011000100001101010111010000 2
b10100100011010101101001001100110 1
b101001 )
b101001 (
#52000
b1 !
b1 .
b1010 #
b1010 *
b1000 &
b1000 -
b11101100001101010001001001000101 %
b11101100001101010001001001000101 ,
b1110000011111100100101101111100 $
b1110000011111100100101101111100 +
b1 /
b1010 0
b1000 3
b11101100001101010001001001000101 2
b1110000011111100100101101111100 1
b101010 )
b101010 (
#53000
b1 !
b1 .
b1100 #
b1100 *
b10100 &
b10100 -
b1000011011001110010010100111101 %
b1000011011001110010010100111101 ,
b11010111011011110111101101011010 $
b11010111011011110111101101011010 +
b1100 0
b10100 3
b1000011011001110010010100111101 2
b11010111011011110111101101011010 1
b101011 )
b101011 (
#54000
b1001100000000000000000010000000 !
b1001100000000000000000010000000 .
b10 #
b10 *
b1110 &
b1110 -
b10110010111111100000101101001101 %
b10110010111111100000101101001101 ,
b10010011100001011111010100111110 $
b10010011100001011111010100111110 +
b1001100000000000000000010000000 /
b10 0
b1110 3
b10110010111111100000101101001101 2
b10010011100001011111010100111110 1
b101100 )
b101100 (
#55000
b1 !
b1 .
b1010 #
b1010 *
b10011 &
b10011 -
b11011111100100000101011110110011 %
b11011111100100000101011110110011 ,
b1001010110001010111111110010100 $
b1001010110001010111111110010100 +
b1 /
b1010 0
b10011 3
b11011111100100000101011110110011 2
b1001010110001010111111110010100 1
b101101 )
b101101 (
#56000
b10000111001011110110001010011010 !
b10000111001011110110001010011010 .
b1000 #
b1000 *
b1001 &
b1001 -
b1101100101011010010111011110101 %
b1101100101011010010111011110101 ,
b11101011100000100100110001101111 $
b11101011100000100100110001101111 +
b10000111001011110110001010011010 /
b1000 0
b1001 3
b1101100101011010010111011110101 2
b11101011100000100100110001101111 1
b101110 )
b101110 (
#57000
b1101000000011010 !
b1101000000011010 .
b101 #
b101 *
b1111 &
b1111 -
b1101000000011010001001110111011 %
b1101000000011010001001110111011 ,
b11111110001111011100111111010000 $
b11111110001111011100111111010000 +
b1101000000011010 /
b101 0
b1111 3
b1101000000011010001001110111011 2
b11111110001111011100111111010000 1
b101111 )
b101111 (
#58000
b10000000001101000000010000010100 !
b10000000001101000000010000010100 .
b10 #
b10 *
b1101 &
b1101 -
b1110110110010110001000100101011 %
b1110110110010110001000100101011 ,
b11101010010011110101011001010 $
b11101010010011110101011001010 +
b10000000001101000000010000010100 /
b10 0
b1101 3
b1110110110010110001000100101011 2
b11101010010011110101011001010 1
b110000 )
b110000 (
#59000
b1 !
b1 .
b1010 #
b1010 *
b11100 &
b11100 -
b11110110101101000111011111101110 %
b11110110101101000111011111101110 ,
b1100110101101000011110100110011 $
b1100110101101000011110100110011 +
b1 /
b1010 0
b11100 3
b11110110101101000111011111101110 2
b1100110101101000011110100110011 1
b110001 )
b110001 (
#60000
b11100111010101100000000000000000 !
b11100111010101100000000000000000 .
b1101 #
b1101 *
b0 &
b0 -
b1011000101111001110011101010110 %
b1011000101111001110011101010110 ,
b10111111111011111110110001011000 $
b10111111111011111110110001011000 +
b11100111010101100000000000000000 /
b1101 0
b0 3
b1011000101111001110011101010110 2
b10111111111011111110110001011000 1
b110010 )
b110010 (
#61000
b101101111111000101010000000000 !
b101101111111000101010000000000 .
b100 #
b100 *
b111 &
b111 -
b11100010110111111100010101000 %
b11100010110111111100010101000 ,
b1001100101110011111001001110110 $
b1001100101110011111001001110110 +
b101101111111000101010000000000 /
b100 0
b111 3
b11100010110111111100010101000 2
b1001100101110011111001001110110 1
b110011 )
b110011 (
#62000
b1011010000001000100000000100000 !
b1011010000001000100000000100000 .
b10 #
b10 *
b0 &
b0 -
b10000101110000110011111011001111 %
b10000101110000110011111011001111 ,
b10100100001110011001101111010100 $
b10100100001110011001101111010100 +
b1011010000001000100000000100000 /
b10 0
b0 3
b10000101110000110011111011001111 2
b10100100001110011001101111010100 1
b110100 )
b110100 (
#63000
b1100110100010 !
b1100110100010 .
b110 #
b110 *
b10001 &
b10001 -
b110011010001000011011010000001 %
b110011010001000011011010000001 ,
b11011001011011010000001111001111 $
b11011001011011010000001111001111 +
b1100110100010 /
b110 0
b10001 3
b110011010001000011011010000001 2
b11011001011011010000001111001111 1
b110101 )
b110101 (
#64000
b100000010110010010100111100010 !
b100000010110010010100111100010 .
b10 #
b10 *
b11001 &
b11001 -
b1010001100001101001010000011101 %
b1010001100001101001010000011101 ,
b10001111001001001100011000011001 $
b10001111001001001100011000011001 +
b100000010110010010100111100010 /
b10 0
b11001 3
b1010001100001101001010000011101 2
b10001111001001001100011000011001 1
b110110 )
b110110 (
#65000
b11111 !
b11111 .
b110 #
b110 *
b111110111100101011111111111011 %
b111110111100101011111111111011 ,
b111000001100110100011000101001 $
b111000001100110100011000101001 +
b11111 /
b110 0
b111110111100101011111111111011 2
b111000001100110100011000101001 1
b110111 )
b110111 (
#66000
b1 !
b1 .
b1010 #
b1010 *
b10000 &
b10000 -
b10111101000000111001010100110010 %
b10111101000000111001010100110010 ,
b10111001010001110011010001001100 $
b10111001010001110011010001001100 +
b1 /
b1010 0
b10000 3
b10111101000000111001010100110010 2
b10111001010001110011010001001100 1
b111000 )
b111000 (
#67000
b11101111100010010110100111011000 !
b11101111100010010110100111011000 .
b1000 #
b1000 *
b11110 &
b11110 -
b10000001111110101100101100101001 %
b10000001111110101100101100101001 ,
b1101110011100111010001011110001 $
b1101110011100111010001011110001 +
b11101111100010010110100111011000 /
b1000 0
b11110 3
b10000001111110101100101100101001 2
b1101110011100111010001011110001 1
b111001 )
b111001 (
#68000
b0 !
b0 .
b1001 #
b1001 *
b1001 &
b1001 -
b10110111010111110111111111101010 %
b10110111010111110111111111101010 ,
b11100101000000101101111010111100 $
b11100101000000101101111010111100 +
b0 /
b1001 0
b1001 3
b10110111010111110111111111101010 2
b11100101000000101101111010111100 1
b111010 )
b111010 (
#69000
b1011110110001010000001100110101 !
b1011110110001010000001100110101 .
b111 #
b111 *
b11010 &
b11010 -
b110010001001000111110010111010 %
b110010001001000111110010111010 ,
b10010000111010010111111111101111 $
b10010000111010010111111111101111 +
b1011110110001010000001100110101 /
b111 0
b11010 3
b110010001001000111110010111010 2
b10010000111010010111111111101111 1
b111011 )
b111011 (
#70000
b0 !
b0 .
b1011 #
b1011 *
b10001 &
b10001 -
b110111100100011010000010110 %
b110111100100011010000010110 ,
b11000101010010011111111001010010 $
b11000101010010011111111001010010 +
b0 /
b1011 0
b10001 3
b110111100100011010000010110 2
b11000101010010011111111001010010 1
b111100 )
b111100 (
#71000
b101011000111001001000011110101 !
b101011000111001001000011110101 .
b1000 #
b1000 *
b11010 &
b11010 -
b100111011010100101001001011011 %
b100111011010100101001001011011 ,
b1100011101101100001010101110 $
b1100011101101100001010101110 +
b101011000111001001000011110101 /
b1000 0
b11010 3
b100111011010100101001001011011 2
b1100011101101100001010101110 1
b111101 )
b111101 (
#72000
b0 !
b0 .
b1001 #
b1001 *
b10010 &
b10010 -
b101011101001000100000111000010 %
b101011101001000100000111000010 ,
b1101001110110101010000000100111 $
b1101001110110101010000000100111 +
b0 /
b1001 0
b10010 3
b101011101001000100000111000010 2
b1101001110110101010000000100111 1
b111110 )
b111110 (
#73000
b1011 #
b1011 *
b1001 &
b1001 -
b1000110000100100010111111110010 %
b1000110000100100010111111110010 ,
b111001110111011001101101110110 $
b111001110111011001101101110110 +
b1011 0
b1001 3
b1000110000100100010111111110010 2
b111001110111011001101101110110 1
b111111 )
b111111 (
#74000
b1 !
b1 .
b1100 #
b1100 *
b11101001100000100001001000000101 %
b11101001100000100001001000000101 ,
b1110010101001001111101100011001 $
b1110010101001001111101100011001 +
b1 /
b1100 0
b11101001100000100001001000000101 2
b1110010101001001111101100011001 1
b1000000 )
b1000000 (
#75000
b110000000110010000 !
b110000000110010000 .
b10 #
b10 *
b10010 &
b10010 -
b11011111111111000111110001101010 %
b11011111111111000111110001101010 ,
b10100001010111001101101000001111 $
b10100001010111001101101000001111 +
b110000000110010000 /
b10 0
b10010 3
b11011111111111000111110001101010 2
b10100001010111001101101000001111 1
b1000001 )
b1000001 (
#76000
b1 !
b1 .
b1001 #
b1001 *
b11000 &
b11000 -
b11101001110100011011110001001000 %
b11101001110100011011110001001000 ,
b11011001001000000101100000100101 $
b11011001001000000101100000100101 +
b1 /
b1001 0
b11000 3
b11101001110100011011110001001000 2
b11011001001000000101100000100101 1
b1000010 )
b1000010 (
#77000
b10011110100111010101001111110010 !
b10011110100111010101001111110010 .
b0 #
b0 *
b100 &
b100 -
b11000110101010000010110101001110 %
b11000110101010000010110101001110 ,
b11010111111101010010011010100100 $
b11010111111101010010011010100100 +
b10011110100111010101001111110010 /
b0 0
b100 3
b11000110101010000010110101001110 2
b11010111111101010010011010100100 1
b1000011 )
b1000011 (
#78000
b11101100010111000111000001100000 !
b11101100010111000111000001100000 .
b100 #
b100 *
b101 &
b101 -
b11011111011000101110001110000011 %
b11011111011000101110001110000011 ,
b10001111101111100001111101011010 $
b10001111101111100001111101011010 +
b11101100010111000111000001100000 /
b100 0
b101 3
b11011111011000101110001110000011 2
b10001111101111100001111101011010 1
b1000100 )
b1000100 (
#79000
b10000111011011111110101001011110 !
b10000111011011111110101001011110 .
b111 #
b111 *
b0 &
b0 -
b11110100110000010001011100000 %
b11110100110000010001011100000 ,
b10100110000010000000110100111110 $
b10100110000010000000110100111110 +
b10000111011011111110101001011110 /
b111 0
b0 3
b11110100110000010001011100000 2
b10100110000010000000110100111110 1
b1000101 )
b1000101 (
#80000
b11000010000100010011101000000000 !
b11000010000100010011101000000000 .
b100 #
b100 *
b1001 &
b1001 -
b11111000111000010000100010011101 %
b11111000111000010000100010011101 ,
b10011000001011111100001101100110 $
b10011000001011111100001101100110 +
b11000010000100010011101000000000 /
b100 0
b1001 3
b11111000111000010000100010011101 2
b10011000001011111100001101100110 1
b1000110 )
b1000110 (
