lab4/HW04_HanJoo/GLOBAL.v
`define		ALU_ADDU			4'b0000
`define		ALU_AND				4'b0001
`define		ALU_NOR				4'b0010
`define		ALU_OR				4'b0011
`define		ALU_SLL				4'b0100
`define		ALU_SRA				4'b0101
`define		ALU_SRL				4'b0110
`define		ALU_SUBU			4'b0111
`define		ALU_XOR				4'b1000
`define		ALU_SLT				4'b1001
`define		ALU_SLTU			4'b1010
`define		ALU_EQ				4'b1011
`define		ALU_NEQ				4'b1100
`define		ALU_LUI				4'b1101

`define		FUNCT_SLL			6'd0
`define		FUNCT_SRL			6'd2
`define		FUNCT_SRA			6'd3
`define 	FUNCT_JR			6'd8
`define		FUNCT_ADDU		6'd33
`define		FUNCT_SUBU		6'd35
`define		FUNCT_AND			6'd36
`define		FUNCT_OR			6'd37
`define		FUNCT_XOR			6'd38
`define		FUNCT_NOR			6'd39
`define		FUNCT_SLT			6'd42
`define		FUNCT_SLTU		6'd43

`define		OP_RTYPE			6'd0
`define		OP_J				  6'd2
`define		OP_JAL				6'd3
`define		OP_BEQ				6'd4
`define		OP_BNE				6'd5
`define		OP_ADDIU			6'd9
`define		OP_SLTI				6'd10
`define		OP_SLTIU			6'd11
`define		OP_ANDI				6'd12
`define		OP_ORI				6'd13
`define		OP_XORI				6'd14
`define		OP_LUI				6'd15
`define		OP_LW			  	6'd35
`define		OP_SW				  6'd43

`define   STATE_IF      3'd0
`define   STATE_ID      3'd1
`define   STATE_EX      3'd2
`define   STATE_MEM     3'd3
`define   STATE_WB      3'd4

lab2/HW02/ALU.v
`timescale 1ns / 1ps
`include "GLOBAL.v"

// this is a combinational logic
module ALU(
		input [31:0]		operand1,
		input [31:0]		operand2,
		input [4:0]			shamt,
		input [3:0]			funct,
		output reg [31:0]	alu_result
	);
	
	// FIXME
	always @(*) begin
		alu_result = 0;
		case (funct)
			`ALU_ADDU:
			alu_result = operand1 + operand2;
			`ALU_AND :
			alu_result = operand1 & operand2;
			`ALU_NOR :
			alu_result = ~(operand1 | operand2);
			`ALU_OR  :
			alu_result = (operand1 | operand2);
			`ALU_SLL :
			alu_result = operand2 << shamt;
			`ALU_SRA :
			alu_result = $signed(operand2) >>> shamt;
			`ALU_SRL :
			alu_result = operand2 >> shamt;
			`ALU_SUBU:
			alu_result = operand1 - operand2;
			`ALU_XOR :
			alu_result = operand1 ^ operand2;
			`ALU_SLT :
			alu_result = $signed(operand1) < $signed(operand2);
			`ALU_SLTU:
			alu_result = operand1 < operand2;
			`ALU_EQ  :
			alu_result = operand1 == operand2;
			`ALU_NEQ :
			alu_result = operand1 != operand2;
			`ALU_LUI :
			alu_result = operand2 << 16;
		endcase
	end
endmodule

lab2/HW02_MinYong/RF.v
`timescale 1ns / 100ps

module RF (
	// You may also change the input and output ports (maybe changing reg to wire)
		input clk,
		input rst,
		// Read-related ports
		input [4:0] rd_addr1,
		input [4:0] rd_addr2,
		// >>>>> should we change the reg output to wire output ?? <<<<<
		output reg [31:0] rd_data1,
		output reg [31:0] rd_data2,
		// Write-related ports
		input RegWrite,
		input [4:0] wr_addr,
		input [31:0] wr_data
	);

    reg [31:0] register_file [0:31];

	
	// Fill in the asynchronous functions
	// async 
	// -> when read address's changes 
	// -> read the data in register file.
	always @(rd_addr1 , rd_addr2) begin
		rd_data1 = register_file[rd_addr1];
		rd_data2 = register_file[rd_addr2];
	end
	// there are no wires to connect.
	//assign ??
    
	always @(posedge clk) begin
		if (rst) begin
			$readmemh("initial_reg.mem", register_file);
		end
		// Since we use reg array variable : register_file as storage.
		// -> non-blocking : "<=" should be used. 
		if(RegWrite) begin
			register_file[wr_addr] <= wr_data;
		end
		// FILL what happens synchronously
	end

endmodule

lab2/HW02_MinYong/TOP.v
`timescale 1ns / 100ps

module TOP(
    input clk,
    input rst,
    
    // Read-related ports
    input [4:0] rd_addr1,
    input [4:0] rd_addr2,
    
    // Write-related ports
    input RegWrite,
    input [4:0] wr_addr,
    
    // ALU ctrl and output
    input [4:0] shamt,
    input [3:0] funct,
    output [31:0] rd_data1,
    output [31:0] rd_data2,
    output [31:0] wr_data
    );
    
	// FIXME
	// Instantiate modules and connect them!
    wire [31:0] net1;
    wire [31:0] net2;
    wire [31:0] net3;
    assign rd_data1 = net1;
    assign rd_data2 = net2; 
    assign wr_data = net3;
    // connecting them explicitly.
    RF rf (
        .clk(clk), 
        .rst(rst), 
        .rd_addr1(rd_addr1), 
        .rd_addr2(rd_addr2),
        .rd_data1(net1),
        .rd_data2(net2),
        .RegWrite(RegWrite),
        .wr_addr(wr_addr),
        .wr_data(net3)
    );
    ALU alu(
        .operand1(net1),
        .operand2(net2),
        .shamt(shamt),
        .funct(funct),
        .alu_result(net3)
    );

endmodule

lab2/HW02_MinYong/TOP_tb.v
`timescale 1ns / 1ps


module TOP_tb;
	parameter TEST_SIZE = 20;
    
    reg clk;
    reg rst;
    reg [4:0] rd_addr1;
    reg [4:0] rd_addr2;
    
    reg RegWrite;
    reg [4:0] wr_addr;
    
    reg [4:0] shamt;
    reg [3:0] funct;
    
	// List of output signals from the RF
    wire [31:0] rd_data1; 
    wire [31:0] rd_data2; 
    wire [31:0] wr_data;  

	reg [4:0]	rd_addr1_mem [0:TEST_SIZE-1];
	reg [4:0]	rd_addr2_mem [0:TEST_SIZE-1];
	reg [4:0]	wr_addr_mem [0:TEST_SIZE-1];
	reg [4:0]	shamt_mem [0:TEST_SIZE-1];
	reg [3:0]  	funct_mem [0:TEST_SIZE-1];
	reg 		RegWrite_mem [0:TEST_SIZE-1];
	reg [31:0] 	rd_data1_mem [0:TEST_SIZE-1];
	reg [31:0] 	rd_data2_mem [0:TEST_SIZE-1];
	reg [31:0] 	wr_data_mem [0:TEST_SIZE-1];

	// Load the data from the memory
	initial begin
		$readmemb("rd_addr1.mem", rd_addr1_mem);
		$readmemb("rd_addr2.mem", rd_addr2_mem);
		$readmemb("wr_addr.mem", wr_addr_mem);
		$readmemb("shamt.mem", shamt_mem);
		$readmemb("funct.mem", funct_mem);
		$readmemb("regwr.mem", RegWrite_mem);
		$readmemh("rd_data1.mem", rd_data1_mem);
		$readmemh("rd_data2.mem", rd_data2_mem);
		$readmemh("wr_data.mem", wr_data_mem);
	end

    TOP top_u (.clk(clk), .rst(rst),
        .rd_addr1(rd_addr1),
		.rd_addr2(rd_addr2),
        .RegWrite(RegWrite),
        .wr_addr(wr_addr),
        .shamt(shamt),
        .funct(funct),
        .rd_data1(rd_data1),
        .rd_data2(rd_data2),
        .wr_data(wr_data)
    );
    
    integer PASSED;
    integer FAILED;
     
    task Test; 
        input [4:0] rd_addr1_in;
        input [4:0] rd_addr2_in;
        input [4:0] wr_addr_in;
        input [4:0] shamt_in;
        input [5:0] funct_in;
        input RegWrite_in;
        input [31:0] rd_data1_in;
        input [31:0] rd_data2_in;
        input [31:0] wr_data_in;
    begin
        #1;
        rd_addr1 = rd_addr1_in;
        rd_addr2 = rd_addr2_in;
        wr_addr = wr_addr_in;
        shamt = shamt_in;
        funct = funct_in;
        RegWrite = RegWrite_in;
        
        #1;
        if (rd_data1 == rd_data1_in &&
			rd_data2 == rd_data2_in &&
			wr_data == wr_data_in) begin
                //$display("PASSED");
                PASSED = PASSED + 1;
        end
        else begin
                $display("FAILED");
                $display("rd_addr1 = %d ", rd_addr1);
                $display("rd_data1 = %h (Ans : %h) ", rd_data1, rd_data1_in,
						 "rd_data2 = %h (Ans : %h) ", rd_data2, rd_data2_in,
						 "wr_data = %h (Ans : %h)", wr_data, wr_data_in);
                FAILED = FAILED + 1;
        end
        // Check prepare for the next cycle
        #8;
    end
    endtask
    
    initial begin
        clk = 1'b0;
        forever #5 clk = ~clk;
    end
    
    initial begin
        $dumpfile("waveform.vcd");
        $dumpvars(0,TOP_tb);
    end

	integer i;
    initial begin
		i = 0;
        PASSED = 0;
        FAILED = 0;
        rst = 1;
        RegWrite = 0;
        #15
        rst = 0;
        #15

		for (i = 0; i < TEST_SIZE; i = i + 1) begin
			Test(rd_addr1_mem[i], rd_addr2_mem[i], wr_addr_mem[i],
				shamt_mem[i], funct_mem[i], RegWrite_mem[i],
				rd_data1_mem[i], rd_data2_mem[i], wr_data_mem[i]);
		end

        #10
        $display("PASSED = %0d, FAILED = %0d", PASSED, FAILED);
        $finish;
    end

endmodule

lab2/HW02_MinYong/waveform.vcd
$date
	Wed Apr  1 20:20:50 2026
$end
$version
	Icarus Verilog
$end
$timescale
	1ps
$end
$scope module TOP_tb $end
$var wire 32 ! wr_data [31:0] $end
$var wire 32 " rd_data2 [31:0] $end
$var wire 32 # rd_data1 [31:0] $end
$var parameter 32 $ TEST_SIZE $end
$var reg 1 % RegWrite $end
$var reg 1 & clk $end
$var reg 4 ' funct [3:0] $end
$var reg 5 ( rd_addr1 [4:0] $end
$var reg 5 ) rd_addr2 [4:0] $end
$var reg 1 * rst $end
$var reg 5 + shamt [4:0] $end
$var reg 5 , wr_addr [4:0] $end
$var integer 32 - FAILED [31:0] $end
$var integer 32 . PASSED [31:0] $end
$var integer 32 / i [31:0] $end
$scope module top_u $end
$var wire 1 % RegWrite $end
$var wire 1 & clk $end
$var wire 4 0 funct [3:0] $end
$var wire 5 1 rd_addr1 [4:0] $end
$var wire 5 2 rd_addr2 [4:0] $end
$var wire 32 3 rd_data1 [31:0] $end
$var wire 32 4 rd_data2 [31:0] $end
$var wire 1 * rst $end
$var wire 5 5 shamt [4:0] $end
$var wire 5 6 wr_addr [4:0] $end
$var wire 32 7 wr_data [31:0] $end
$var wire 32 8 net3 [31:0] $end
$var wire 32 9 net2 [31:0] $end
$var wire 32 : net1 [31:0] $end
$scope module alu $end
$var wire 4 ; funct [3:0] $end
$var wire 5 < shamt [4:0] $end
$var wire 32 = operand2 [31:0] $end
$var wire 32 > operand1 [31:0] $end
$var reg 32 ? alu_result [31:0] $end
$upscope $end
$scope module rf $end
$var wire 1 % RegWrite $end
$var wire 1 & clk $end
$var wire 5 @ rd_addr1 [4:0] $end
$var wire 5 A rd_addr2 [4:0] $end
$var wire 1 * rst $end
$var wire 5 B wr_addr [4:0] $end
$var wire 32 C wr_data [31:0] $end
$var reg 32 D rd_data1 [31:0] $end
$var reg 32 E rd_data2 [31:0] $end
$upscope $end
$upscope $end
$scope task Test $end
$var reg 1 F RegWrite_in $end
$var reg 6 G funct_in [5:0] $end
$var reg 5 H rd_addr1_in [4:0] $end
$var reg 5 I rd_addr2_in [4:0] $end
$var reg 32 J rd_data1_in [31:0] $end
$var reg 32 K rd_data2_in [31:0] $end
$var reg 5 L shamt_in [4:0] $end
$var reg 5 M wr_addr_in [4:0] $end
$var reg 32 N wr_data_in [31:0] $end
$upscope $end
$upscope $end
$enddefinitions $end
$comment Show the parameter values. $end
$dumpall
b10011100010000 $
$end
#0
$dumpvars
bx N
bx M
bx L
bx K
bx J
bx I
bx H
bx G
xF
bx E
bx D
bx C
bx B
bx A
bx @
bx ?
bx >
bx =
bx <
bx ;
bx :
bx 9
bx 8
bx 7
bx 6
bx 5
bx 4
bx 3
bx 2
bx 1
bx 0
b0 /
b0 .
b0 -
bx ,
bx +
1*
bx )
bx (
bx '
0&
0%
bx #
bx "
bx !
$end
#5000
1&
#10000
0&
#15000
1&
0*
#20000
0&
#25000
1&
b11110011111110110111101111111110 N
b1110001111100010011100010100000 K
b11000010101110100101001111111110 J
1F
b11 G
b1 L
b11110 M
b1001 I
b10000 H
#26000
b11110011111110110111101111111110 !
b11110011111110110111101111111110 7
b11110011111110110111101111111110 8
b11110011111110110111101111111110 ?
b11110011111110110111101111111110 C
b1110001111100010011100010100000 "
b1110001111100010011100010100000 4
b1110001111100010011100010100000 9
b1110001111100010011100010100000 =
b1110001111100010011100010100000 E
b11000010101110100101001111111110 #
b11000010101110100101001111111110 3
b11000010101110100101001111111110 :
b11000010101110100101001111111110 >
b11000010101110100101001111111110 D
1%
b11 '
b11 0
b11 ;
b1 +
b1 5
b1 <
b11110 ,
b11110 6
b11110 B
b1001 )
b1001 2
b1001 A
b10000 (
b10000 1
b10000 @
#27000
b1 .
#30000
0&
#35000
1&
b1 N
b1101001000010110011010100001100 K
b10010111111011010010110011110 J
b1010 G
b111 I
b11100 H
b1 /
#36000
b1 !
b1 7
b1 8
b1 ?
b1 C
b1101001000010110011010100001100 "
b1101001000010110011010100001100 4
b1101001000010110011010100001100 9
b1101001000010110011010100001100 =
b1101001000010110011010100001100 E
b10010111111011010010110011110 #
b10010111111011010010110011110 3
b10010111111011010010110011110 :
b10010111111011010010110011110 >
b10010111111011010010110011110 D
b1010 '
b1010 0
b1010 ;
b111 )
b111 2
b111 A
b11100 (
b11100 1
b11100 @
#37000
b10 .
#40000
0&
#45000
1&
b10000010001011000101010000000 N
b10010111111011010010110011110 K
b100011010000110011000000011110 J
0F
b111 G
b10110 L
b1011 M
b11100 I
b1010 H
b10 /
#46000
b10000010001011000101010000000 !
b10000010001011000101010000000 7
b10000010001011000101010000000 8
b10000010001011000101010000000 ?
b10000010001011000101010000000 C
b10010111111011010010110011110 "
b10010111111011010010110011110 4
b10010111111011010010110011110 9
b10010111111011010010110011110 =
b10010111111011010010110011110 E
b100011010000110011000000011110 #
b100011010000110011000000011110 3
b100011010000110011000000011110 :
b100011010000110011000000011110 >
b100011010000110011000000011110 D
0%
b111 '
b111 0
b111 ;
b10110 +
b10110 5
b10110 <
b1011 ,
b1011 6
b1011 B
b11100 )
b11100 2
b11100 A
b1010 (
b1010 1
b1010 @
#47000
b11 .
#50000
0&
#55000
1&
b11101111101110100111010110000000 N
b100011010000110011000000011110 K
b10010111111011010010110011110 J
1F
b10000 L
b1100 M
b1010 I
b11100 H
b11 /
#56000
b11101111101110100111010110000000 !
b11101111101110100111010110000000 7
b11101111101110100111010110000000 8
b11101111101110100111010110000000 ?
b11101111101110100111010110000000 C
b100011010000110011000000011110 "
b100011010000110011000000011110 4
b100011010000110011000000011110 9
b100011010000110011000000011110 =
b100011010000110011000000011110 E
b10010111111011010010110011110 #
b10010111111011010010110011110 3
b10010111111011010010110011110 :
b10010111111011010010110011110 >
b10010111111011010010110011110 D
1%
b10000 +
b10000 5
b10000 <
b1100 ,
b1100 6
b1100 B
b1010 )
b1010 2
b1010 A
b11100 (
b11100 1
b11100 @
#57000
b100 .
#60000
0&
#65000
1&
b1 N
b11101110101101111001000100101100 K
b11111010110111110101100010111010 J
0F
b1100 G
b10100 L
b11100 M
b1111 I
b10010 H
b100 /
#66000
b1 !
b1 7
b1 8
b1 ?
b1 C
b11101110101101111001000100101100 "
b11101110101101111001000100101100 4
b11101110101101111001000100101100 9
b11101110101101111001000100101100 =
b11101110101101111001000100101100 E
b11111010110111110101100010111010 #
b11111010110111110101100010111010 3
b11111010110111110101100010111010 :
b11111010110111110101100010111010 >
b11111010110111110101100010111010 D
0%
b1100 '
b1100 0
b1100 ;
b10100 +
b10100 5
b10100 <
b11100 ,
b11100 6
b11100 B
b1111 )
b1111 2
b1111 A
b10010 (
b10010 1
b10010 @
#67000
b101 .
#70000
0&
#75000
1&
b1111000000000000000000000000000 N
b10010111111011010010110011110 K
b10000100011101100111010111001 J
1F
b100 G
b11010 L
b10 M
b11100 I
b11011 H
b101 /
#76000
b1111000000000000000000000000000 !
b1111000000000000000000000000000 7
b1111000000000000000000000000000 8
b1111000000000000000000000000000 ?
b1111000000000000000000000000000 C
b10010111111011010010110011110 "
b10010111111011010010110011110 4
b10010111111011010010110011110 9
b10010111111011010010110011110 =
b10010111111011010010110011110 E
b10000100011101100111010111001 #
b10000100011101100111010111001 3
b10000100011101100111010111001 :
b10000100011101100111010111001 >
b10000100011101100111010111001 D
1%
b100 '
b100 0
b100 ;
b11010 +
b11010 5
b11010 <
b10 ,
b10 6
b10 B
b11100 )
b11100 2
b11100 A
b11011 (
b11011 1
b11011 @
#77000
b110 .
#80000
0&
#85000
1&
b10001000101010101000 N
b10000110000110011000101111101010 K
b1 G
b1010 M
b11010 I
b110 /
#86000
b10001000101010101000 !
b10001000101010101000 7
b10001000101010101000 8
b10001000101010101000 ?
b10001000101010101000 C
b10000110000110011000101111101010 "
b10000110000110011000101111101010 4
b10000110000110011000101111101010 9
b10000110000110011000101111101010 =
b10000110000110011000101111101010 E
b1 '
b1 0
b1 ;
b1010 ,
b1010 6
b1010 B
b11010 )
b11010 2
b11010 A
#87000
b111 .
#90000
0&
#95000
1&
b1001 N
b10011111000110011010001011011111 K
b11100110010100100111011111010001 J
0F
b110 G
b11100 L
b101 M
b110 I
b10001 H
b111 /
#96000
b1001 !
b1001 7
b1001 8
b1001 ?
b1001 C
b10011111000110011010001011011111 "
b10011111000110011010001011011111 4
b10011111000110011010001011011111 9
b10011111000110011010001011011111 =
b10011111000110011010001011011111 E
b11100110010100100111011111010001 #
b11100110010100100111011111010001 3
b11100110010100100111011111010001 :
b11100110010100100111011111010001 >
b11100110010100100111011111010001 D
0%
b110 '
b110 0
b110 ;
b11100 +
b11100 5
b11100 <
b101 ,
b101 6
b101 B
b110 )
b110 2
b110 A
b10001 (
b10001 1
b10001 @
#97000
b1000 .
#100000
0&
#105000
1&
b1001101001100111111110100011001 N
b10001011010111110000100000001000 K
b11011000100100110000010100100001 J
1F
b111 G
b1 L
b11110 M
b11000 I
b10101 H
b1000 /
#106000
b1001101001100111111110100011001 !
b1001101001100111111110100011001 7
b1001101001100111111110100011001 8
b1001101001100111111110100011001 ?
b1001101001100111111110100011001 C
b10001011010111110000100000001000 "
b10001011010111110000100000001000 4
b10001011010111110000100000001000 9
b10001011010111110000100000001000 =
b10001011010111110000100000001000 E
b11011000100100110000010100100001 #
b11011000100100110000010100100001 3
b11011000100100110000010100100001 :
b11011000100100110000010100100001 >
b11011000100100110000010100100001 D
1%
b111 '
b111 0
b111 ;
b1 +
b1 5
b1 <
b11110 ,
b11110 6
b11110 B
b11000 )
b11000 2
b11000 A
b10101 (
b10101 1
b10101 @
#107000
b1001 .
#110000
0&
#115000
1&
b10010111111111110111110111111 N
b10000100011101100111010111001 K
b10010111111011010010110011110 J
b11 G
b11001 L
b1000 M
b11011 I
b11100 H
b1001 /
#116000
b10010111111111110111110111111 !
b10010111111111110111110111111 7
b10010111111111110111110111111 8
b10010111111111110111110111111 ?
b10010111111111110111110111111 C
b10000100011101100111010111001 "
b10000100011101100111010111001 4
b10000100011101100111010111001 9
b10000100011101100111010111001 =
b10000100011101100111010111001 E
b10010111111011010010110011110 #
b10010111111011010010110011110 3
b10010111111011010010110011110 :
b10010111111011010010110011110 >
b10010111111011010010110011110 D
b11 '
b11 0
b11 ;
b11001 +
b11001 5
b11001 <
b1000 ,
b1000 6
b1000 B
b11011 )
b11011 2
b11011 A
b11100 (
b11100 1
b11100 @
#117000
b1010 .
#120000
0&
#125000
1&
b10000010000100000101011101010001 N
b10001010000100001101111101011011 K
b11100110010100100111011111010001 J
b1 G
b10011 L
b10001 M
b1011 I
b10001 H
b1010 /
#126000
b10000010000100000101011101010001 !
b10000010000100000101011101010001 7
b10000010000100000101011101010001 8
b10000010000100000101011101010001 ?
b10000010000100000101011101010001 C
b10001010000100001101111101011011 "
b10001010000100001101111101011011 4
b10001010000100001101111101011011 9
b10001010000100001101111101011011 =
b10001010000100001101111101011011 E
b11100110010100100111011111010001 #
b11100110010100100111011111010001 3
b11100110010100100111011111010001 :
b11100110010100100111011111010001 >
b11100110010100100111011111010001 D
b1 '
b1 0
b1 ;
b10011 +
b10011 5
b10011 <
b10001 ,
b10001 6
b10001 B
b1011 )
b1011 2
b1011 A
b10001 (
b10001 1
b10001 @
#127000
b1011 .
#130000
0&
#135000
1&
b1001101111110000001111100000100 N
b1001100100011010111010010100 K
b1000100011010011011000110010000 J
b1000 G
b1 L
b1001 M
b0 I
b10111 H
b1011 /
#136000
b1001101111110000001111100000100 !
b1001101111110000001111100000100 7
b1001101111110000001111100000100 8
b1001101111110000001111100000100 ?
b1001101111110000001111100000100 C
b1001100100011010111010010100 "
b1001100100011010111010010100 4
b1001100100011010111010010100 9
b1001100100011010111010010100 =
b1001100100011010111010010100 E
b1000100011010011011000110010000 #
b1000100011010011011000110010000 3
b1000100011010011011000110010000 :
b1000100011010011011000110010000 >
b1000100011010011011000110010000 D
b1000 '
b1000 0
b1000 ;
b1 +
b1 5
b1 <
b1001 ,
b1001 6
b1001 B
b0 )
b0 2
b0 A
b10111 (
b10111 1
b10111 @
#137000
b1100 .
#140000
0&
#145000
1&
b10001010000110010110101000000011 N
b10001010000100001101111101011011 K
b10001000101010101000 J
b0 G
b10000 L
b1011 M
b1011 I
b1010 H
b1100 /
#146000
b10001010000110010110101000000011 !
b10001010000110010110101000000011 7
b10001010000110010110101000000011 8
b10001010000110010110101000000011 ?
b10001010000110010110101000000011 C
b10001010000100001101111101011011 "
b10001010000100001101111101011011 4
b10001010000100001101111101011011 9
b10001010000100001101111101011011 =
b10001010000100001101111101011011 E
b10001000101010101000 #
b10001000101010101000 3
b10001000101010101000 :
b10001000101010101000 >
b10001000101010101000 D
b0 '
b0 0
b0 ;
b10000 +
b10000 5
b10000 <
b1011 ,
b1011 6
b1011 B
b1011 )
b1011 2
b1011 A
b1010 (
b1010 1
b1010 @
#147000
b1101 .
#150000
0&
#155000
1&
b0 N
b1111101001111110111011100101001 K
b10001110000001001011101100011111 J
0F
b1010 G
b11 L
b11111 M
b11101 I
b100 H
b1101 /
#156000
b0 !
b0 7
b0 8
b0 ?
b0 C
b1111101001111110111011100101001 "
b1111101001111110111011100101001 4
b1111101001111110111011100101001 9
b1111101001111110111011100101001 =
b1111101001111110111011100101001 E
b10001110000001001011101100011111 #
b10001110000001001011101100011111 3
b10001110000001001011101100011111 :
b10001110000001001011101100011111 >
b10001110000001001011101100011111 D
0%
b1010 '
b1010 0
b1010 ;
b11 +
b11 5
b11 <
b11111 ,
b11111 6
b11111 B
b11101 )
b11101 2
b11101 A
b100 (
b100 1
b100 @
#157000
b1110 .
#160000
0&
#165000
1&
b10001110110011101011100100000 N
b10000100011101100111010111001 K
b10010111111011010010110011110 J
1F
b100 G
b101 L
b100 M
b11011 I
b11100 H
b1110 /
#166000
b10001110110011101011100100000 !
b10001110110011101011100100000 7
b10001110110011101011100100000 8
b10001110110011101011100100000 ?
b10001110110011101011100100000 C
b10000100011101100111010111001 "
b10000100011101100111010111001 4
b10000100011101100111010111001 9
b10000100011101100111010111001 =
b10000100011101100111010111001 E
b10010111111011010010110011110 #
b10010111111011010010110011110 3
b10010111111011010010110011110 :
b10010111111011010010110011110 >
b10010111111011010010110011110 D
1%
b100 '
b100 0
b100 ;
b101 +
b101 5
b101 <
b100 ,
b100 6
b100 B
b11011 )
b11011 2
b11011 A
b11100 (
b11100 1
b11100 @
#167000
b1111 .
#170000
0&
#175000
1&
b0 N
b11001010101101011000100100011111 K
b10000110000110011000101111101010 J
b1011 G
b1011 L
b11110 M
b101 I
b11010 H
b1111 /
#176000
b0 !
b0 7
b0 8
b0 ?
b0 C
b11001010101101011000100100011111 "
b11001010101101011000100100011111 4
b11001010101101011000100100011111 9
b11001010101101011000100100011111 =
b11001010101101011000100100011111 E
b10000110000110011000101111101010 #
b10000110000110011000101111101010 3
b10000110000110011000101111101010 :
b10000110000110011000101111101010 >
b10000110000110011000101111101010 D
b1011 '
b1011 0
b1011 ;
b1011 +
b1011 5
b1011 <
b11110 ,
b11110 6
b11110 B
b101 )
b101 2
b101 A
b11010 (
b11010 1
b11010 @
#177000
b10000 .
#180000
0&
#185000
1&
b1010011111111100000000000000000 N
b11000010101110100101001111111110 K
b10000100011101100111010111001 J
0F
b1101 G
b100 L
b100 M
b10000 I
b11011 H
b10000 /
#186000
b1010011111111100000000000000000 !
b1010011111111100000000000000000 7
b1010011111111100000000000000000 8
b1010011111111100000000000000000 ?
b1010011111111100000000000000000 C
b11000010101110100101001111111110 "
b11000010101110100101001111111110 4
b11000010101110100101001111111110 9
b11000010101110100101001111111110 =
b11000010101110100101001111111110 E
b10000100011101100111010111001 #
b10000100011101100111010111001 3
b10000100011101100111010111001 :
b10000100011101100111010111001 >
b10000100011101100111010111001 D
0%
b1101 '
b1101 0
b1101 ;
b100 +
b100 5
b100 <
b100 ,
b100 6
b100 B
b10000 )
b10000 2
b10000 A
b11011 (
b11011 1
b11011 @
#187000
b10001 .
#190000
0&
#195000
1&
b1011001111000000000000000000000 N
b10010111111011010010110011110 K
b1001101111110000001111100000100 J
b100 G
b10100 L
b1010 M
b11100 I
b1001 H
b10001 /
#196000
b1011001111000000000000000000000 !
b1011001111000000000000000000000 7
b1011001111000000000000000000000 8
b1011001111000000000000000000000 ?
b1011001111000000000000000000000 C
b10010111111011010010110011110 "
b10010111111011010010110011110 4
b10010111111011010010110011110 9
b10010111111011010010110011110 =
b10010111111011010010110011110 E
b1001101111110000001111100000100 #
b1001101111110000001111100000100 3
b1001101111110000001111100000100 :
b1001101111110000001111100000100 >
b1001101111110000001111100000100 D
b100 '
b100 0
b100 ;
b10100 +
b10100 5
b10100 <
b1010 ,
b1010 6
b1010 B
b11100 )
b11100 2
b11100 A
b1001 (
b1001 1
b1001 @
#197000
b10010 .
#200000
0&
#205000
1&
b11010010101111101101111111111111 N
b11000010101110100101001111111110 K
b10000100011101100111010111001 J
1F
b11 G
b11011 L
b1111 M
b10000 I
b11011 H
b10010 /
#206000
b11010010101111101101111111111111 !
b11010010101111101101111111111111 7
b11010010101111101101111111111111 8
b11010010101111101101111111111111 ?
b11010010101111101101111111111111 C
b11000010101110100101001111111110 "
b11000010101110100101001111111110 4
b11000010101110100101001111111110 9
b11000010101110100101001111111110 =
b11000010101110100101001111111110 E
b10000100011101100111010111001 #
b10000100011101100111010111001 3
b10000100011101100111010111001 :
b10000100011101100111010111001 >
b10000100011101100111010111001 D
1%
b11 '
b11 0
b11 ;
b11011 +
b11011 5
b11011 <
b1111 ,
b1111 6
b1111 B
b10000 )
b10000 2
b10000 A
b11011 (
b11011 1
b11011 @
#207000
b10011 .
#210000
0&
#215000
1&
b11110101011011000010110110000010 N
b10111000001001101000000110000000 J
0F
b111 G
b111 L
b1000 M
b11 H
b10011 /
#216000
b11110101011011000010110110000010 !
b11110101011011000010110110000010 7
b11110101011011000010110110000010 8
b11110101011011000010110110000010 ?
b11110101011011000010110110000010 C
b10111000001001101000000110000000 #
b10111000001001101000000110000000 3
b10111000001001101000000110000000 :
b10111000001001101000000110000000 >
b10111000001001101000000110000000 D
0%
b111 '
b111 0
b111 ;
b111 +
b111 5
b111 <
b1000 ,
b1000 6
b1000 B
b11 (
b11 1
b11 @
#217000
b10100 .
#220000
0&
#225000
1&
b11100011010011011010111010111000 N
b11010010101111101101111111111111 K
b10000100011101100111010111001 J
1F
b0 G
b11001 L
b10 M
b1111 I
b11011 H
b10100 /
#226000
b11100011010011011010111010111000 !
b11100011010011011010111010111000 7
b11100011010011011010111010111000 8
b11100011010011011010111010111000 ?
b11100011010011011010111010111000 C
b11010010101111101101111111111111 "
b11010010101111101101111111111111 4
b11010010101111101101111111111111 9
b11010010101111101101111111111111 =
b11010010101111101101111111111111 E
b10000100011101100111010111001 #
b10000100011101100111010111001 3
b10000100011101100111010111001 :
b10000100011101100111010111001 >
b10000100011101100111010111001 D
1%
b0 '
b0 0
b0 ;
b11001 +
b11001 5
b11001 <
b10 ,
b10 6
b10 B
b1111 )
b1111 2
b1111 A
b11011 (
b11011 1
b11011 @
#227000
b10101 .
#230000
0&
#235000
1&
b1 N
b11011000100100110000010100100001 K
b1111101001111110111011100101001 J
0F
b1010 G
b1 L
b1011 M
b10101 I
b11101 H
b10101 /
#236000
b1 !
b1 7
b1 8
b1 ?
b1 C
b11011000100100110000010100100001 "
b11011000100100110000010100100001 4
b11011000100100110000010100100001 9
b11011000100100110000010100100001 =
b11011000100100110000010100100001 E
b1111101001111110111011100101001 #
b1111101001111110111011100101001 3
b1111101001111110111011100101001 :
b1111101001111110111011100101001 >
b1111101001111110111011100101001 D
0%
b1010 '
b1010 0
b1010 ;
b1 +
b1 5
b1 <
b1011 ,
b1011 6
b1011 B
b10101 )
b10101 2
b10101 A
b11101 (
b11101 1
b11101 @
#237000
b10110 .
#240000
0&
#245000
1&
b10111000001001101000000 N
b10111000001001101000000110000000 K
b1010011111000100000110000111111 J
b110 G
b1001 L
b11000 M
b11 I
b11111 H
b10110 /
#246000
b10111000001001101000000 !
b10111000001001101000000 7
b10111000001001101000000 8
b10111000001001101000000 ?
b10111000001001101000000 C
b10111000001001101000000110000000 "
b10111000001001101000000110000000 4
b10111000001001101000000110000000 9
b10111000001001101000000110000000 =
b10111000001001101000000110000000 E
b1010011111000100000110000111111 #
b1010011111000100000110000111111 3
b1010011111000100000110000111111 :
b1010011111000100000110000111111 >
b1010011111000100000110000111111 D
b110 '
b110 0
b110 ;
b1001 +
b1001 5
b1001 <
b11000 ,
b11000 6
b11000 B
b11 )
b11 2
b11 A
b11111 (
b11111 1
b11111 @
#247000
b10111 .
#250000
0&
#255000
1&
b10111110001011010000100101011001 N
b10101101100111100011101010100000 K
b10000100011101100111010111001 J
b0 G
b1010 L
b10101 M
b10011 I
b11011 H
b10111 /
#256000
b10111110001011010000100101011001 !
b10111110001011010000100101011001 7
b10111110001011010000100101011001 8
b10111110001011010000100101011001 ?
b10111110001011010000100101011001 C
b10101101100111100011101010100000 "
b10101101100111100011101010100000 4
b10101101100111100011101010100000 9
b10101101100111100011101010100000 =
b10101101100111100011101010100000 E
b10000100011101100111010111001 #
b10000100011101100111010111001 3
b10000100011101100111010111001 :
b10000100011101100111010111001 >
b10000100011101100111010111001 D
b0 '
b0 0
b0 ;
b1010 +
b1010 5
b1010 <
b10101 ,
b10101 6
b10101 B
b10011 )
b10011 2
b10011 A
b11011 (
b11011 1
b11011 @
#257000
b11000 .
#260000
0&
