lab4/HW04_HanJoo/GLOBAL.v
`define		ALU_ADDU			4'b0000
`define		ALU_AND				4'b0001
`define		ALU_NOR				4'b0010
`define		ALU_OR				4'b0011
`define		ALU_SLL				4'b0100
`define		ALU_SRA				4'b0101
`define		ALU_SRL				4'b0110
`define		ALU_SUBU			4'b0111
`define		ALU_XOR				4'b1000
`define		ALU_SLT				4'b1001
`define		ALU_SLTU			4'b1010
`define		ALU_EQ				4'b1011
`define		ALU_NEQ				4'b1100
`define		ALU_LUI				4'b1101

`define		FUNCT_SLL			6'd0
`define		FUNCT_SRL			6'd2
`define		FUNCT_SRA			6'd3
`define 	FUNCT_JR			6'd8
`define		FUNCT_ADDU		6'd33
`define		FUNCT_SUBU		6'd35
`define		FUNCT_AND			6'd36
`define		FUNCT_OR			6'd37
`define		FUNCT_XOR			6'd38
`define		FUNCT_NOR			6'd39
`define		FUNCT_SLT			6'd42
`define		FUNCT_SLTU		6'd43

`define		OP_RTYPE			6'd0
`define		OP_J				  6'd2
`define		OP_JAL				6'd3
`define		OP_BEQ				6'd4
`define		OP_BNE				6'd5
`define		OP_ADDIU			6'd9
`define		OP_SLTI				6'd10
`define		OP_SLTIU			6'd11
`define		OP_ANDI				6'd12
`define		OP_ORI				6'd13
`define		OP_XORI				6'd14
`define		OP_LUI				6'd15
`define		OP_LW			  	6'd35
`define		OP_SW				  6'd43

`define   STATE_IF      3'd0
`define   STATE_ID      3'd1
`define   STATE_EX      3'd2
`define   STATE_MEM     3'd3
`define   STATE_WB      3'd4

lab2/HW02/ALU.v
`timescale 1ns / 1ps
`include "GLOBAL.v"

// this is a combinational logic
module ALU(
		input [31:0]		operand1,
		input [31:0]		operand2,
		input [4:0]			shamt,
		input [3:0]			funct,
		output reg [31:0]	alu_result
	);
	
	// FIXME
	always @(*) begin
		alu_result = 0;
		case (funct)
			`ALU_ADDU:
			alu_result = operand1 + operand2;
			`ALU_AND :
			alu_result = operand1 & operand2;
			`ALU_NOR :
			alu_result = ~(operand1 | operand2);
			`ALU_OR  :
			alu_result = (operand1 | operand2);
			`ALU_SLL :
			alu_result = operand2 << shamt;
			`ALU_SRA :
			alu_result = $signed(operand2) >>> shamt;
			`ALU_SRL :
			alu_result = operand2 >> shamt;
			`ALU_SUBU:
			alu_result = operand1 - operand2;
			`ALU_XOR :
			alu_result = operand1 ^ operand2;
			`ALU_SLT :
			alu_result = $signed(operand1) < $signed(operand2);
			`ALU_SLTU:
			alu_result = operand1 < operand2;
			`ALU_EQ  :
			alu_result = operand1 == operand2;
			`ALU_NEQ :
			alu_result = operand1 != operand2;
			`ALU_LUI :
			alu_result = operand2 << 16;
		endcase
	end
endmodule

lab2/HW02/RF.v
`timescale 1ns / 100ps

module RF (
	// You may also change the input and output ports (maybe changing reg to wire)
		input clk,
		input rst,
		// Read-related ports
		input [4:0] rd_addr1,
		input [4:0] rd_addr2,
		output reg [31:0] rd_data1,
		output reg [31:0] rd_data2,
		// Write-related ports
		input RegWrite,
		input [4:0] wr_addr,
		input [31:0] wr_data
	);

    reg [31:0] register_file [0:31];

	
	// Fill in the asynchronous functions
	always @(*) begin
		rd_data1 = register_file[rd_addr1];
		rd_data2 = register_file[rd_addr2];
	end
    
	always @(posedge clk) begin
		if (rst) begin
			$readmemh("initial_reg.mem", register_file);
		end
		// FILL what happens synchronously
		if (RegWrite) begin
			register_file[wr_addr] = wr_data;
		end
	end

endmodule

lab2/HW02/TOP.v
`timescale 1ns / 100ps

module TOP(
    input clk,
    input rst,
    
    // Read-related ports
    input [4:0] rd_addr1,
    input [4:0] rd_addr2,
    
    // Write-related ports
    input RegWrite,
    input [4:0] wr_addr,
    
    // ALU ctrl and output
    input [4:0] shamt,
    input [3:0] funct,
    output [31:0] rd_data1,
    output [31:0] rd_data2,
    output [31:0] wr_data
    );
    
	// FIXME
	// Instantiate modules and connect them!
    RF rf (clk, rst, rd_addr1, rd_addr2, rd_data1, rd_data2, RegWrite, wr_addr, wr_data);
    ALU alu (rd_data1, rd_data2, shamt, funct, rf.wr_data);

    // RF input
    // rf.wr_data = alu.alu_result;
    // rf.rd_addr1 = rd_addr1;
    // rf.rd_addr2 = rd_addr2;
    // rf.wr_addr = wr_addr;
    // rf.RegWrite = RegWrite;
    // rf.clk = clk;
    // rf.rst = rst;

    // // RF output
    // rd_data1 = rf.rd_data1;
    // rd_data2 = rf.rd_data2;

    // // ALU input
    // alu.operand1 = rf.rd_data1;
    // alu.operand2 = rf.rd_data2;
    // alu.funct = funct;
    // alu.shamt = shant;

    // // ALU output
    // alu_result = alu.alu_result;

    
endmodule

lab2/HW02_MinYong/TOP_tb.v
`timescale 1ns / 1ps


module TOP_tb;
	parameter TEST_SIZE = 20;
    
    reg clk;
    reg rst;
    reg [4:0] rd_addr1;
    reg [4:0] rd_addr2;
    
    reg RegWrite;
    reg [4:0] wr_addr;
    
    reg [4:0] shamt;
    reg [3:0] funct;
    
	// List of output signals from the RF
    wire [31:0] rd_data1; 
    wire [31:0] rd_data2; 
    wire [31:0] wr_data;  

	reg [4:0]	rd_addr1_mem [0:TEST_SIZE-1];
	reg [4:0]	rd_addr2_mem [0:TEST_SIZE-1];
	reg [4:0]	wr_addr_mem [0:TEST_SIZE-1];
	reg [4:0]	shamt_mem [0:TEST_SIZE-1];
	reg [3:0]  	funct_mem [0:TEST_SIZE-1];
	reg 		RegWrite_mem [0:TEST_SIZE-1];
	reg [31:0] 	rd_data1_mem [0:TEST_SIZE-1];
	reg [31:0] 	rd_data2_mem [0:TEST_SIZE-1];
	reg [31:0] 	wr_data_mem [0:TEST_SIZE-1];

	// Load the data from the memory
	initial begin
		$readmemb("rd_addr1.mem", rd_addr1_mem);
		$readmemb("rd_addr2.mem", rd_addr2_mem);
		$readmemb("wr_addr.mem", wr_addr_mem);
		$readmemb("shamt.mem", shamt_mem);
		$readmemb("funct.mem", funct_mem);
		$readmemb("regwr.mem", RegWrite_mem);
		$readmemh("rd_data1.mem", rd_data1_mem);
		$readmemh("rd_data2.mem", rd_data2_mem);
		$readmemh("wr_data.mem", wr_data_mem);
	end

    TOP top_u (.clk(clk), .rst(rst),
        .rd_addr1(rd_addr1),
		.rd_addr2(rd_addr2),
        .RegWrite(RegWrite),
        .wr_addr(wr_addr),
        .shamt(shamt),
        .funct(funct),
        .rd_data1(rd_data1),
        .rd_data2(rd_data2),
        .wr_data(wr_data)
    );
    
    integer PASSED;
    integer FAILED;
     
    task Test; 
        input [4:0] rd_addr1_in;
        input [4:0] rd_addr2_in;
        input [4:0] wr_addr_in;
        input [4:0] shamt_in;
        input [5:0] funct_in;
        input RegWrite_in;
        input [31:0] rd_data1_in;
        input [31:0] rd_data2_in;
        input [31:0] wr_data_in;
    begin
        #1;
        rd_addr1 = rd_addr1_in;
        rd_addr2 = rd_addr2_in;
        wr_addr = wr_addr_in;
        shamt = shamt_in;
        funct = funct_in;
        RegWrite = RegWrite_in;
        
        #1;
        if (rd_data1 == rd_data1_in &&
			rd_data2 == rd_data2_in &&
			wr_data == wr_data_in) begin
                //$display("PASSED");
                PASSED = PASSED + 1;
        end
        else begin
                $display("FAILED");
                $display("rd_addr1 = %d ", rd_addr1);
                $display("rd_data1 = %h (Ans : %h) ", rd_data1, rd_data1_in,
						 "rd_data2 = %h (Ans : %h) ", rd_data2, rd_data2_in,
						 "wr_data = %h (Ans : %h)", wr_data, wr_data_in);
                FAILED = FAILED + 1;
        end
        // Check prepare for the next cycle
        #8;
    end
    endtask
    
    initial begin
        clk = 1'b0;
        forever #5 clk = ~clk;
    end
    
    initial begin
        $dumpfile("waveform.vcd");
        $dumpvars(0,TOP_tb);
    end

	integer i;
    initial begin
		i = 0;
        PASSED = 0;
        FAILED = 0;
        rst = 1;
        RegWrite = 0;
        #15
        rst = 0;
        #15

		for (i = 0; i < TEST_SIZE; i = i + 1) begin
			Test(rd_addr1_mem[i], rd_addr2_mem[i], wr_addr_mem[i],
				shamt_mem[i], funct_mem[i], RegWrite_mem[i],
				rd_data1_mem[i], rd_data2_mem[i], wr_data_mem[i]);
		end

        #10
        $display("PASSED = %0d, FAILED = %0d", PASSED, FAILED);
        $finish;
    end

endmodule

lab2/HW02/waveform.vcd
$date
	Wed Apr  1 15:49:47 2026
$end
$version
	Icarus Verilog
$end
$timescale
	1ps
$end
$scope module TOP_tb $end
$var wire 32 ! wr_data [31:0] $end
$var wire 32 " rd_data2 [31:0] $end
$var wire 32 # rd_data1 [31:0] $end
$var parameter 32 $ TEST_SIZE $end
$var reg 1 % RegWrite $end
$var reg 1 & clk $end
$var reg 4 ' funct [3:0] $end
$var reg 5 ( rd_addr1 [4:0] $end
$var reg 5 ) rd_addr2 [4:0] $end
$var reg 1 * rst $end
$var reg 5 + shamt [4:0] $end
$var reg 5 , wr_addr [4:0] $end
$var integer 32 - FAILED [31:0] $end
$var integer 32 . PASSED [31:0] $end
$var integer 32 / i [31:0] $end
$scope module top_u $end
$var wire 1 % RegWrite $end
$var wire 1 & clk $end
$var wire 4 0 funct [3:0] $end
$var wire 5 1 rd_addr1 [4:0] $end
$var wire 5 2 rd_addr2 [4:0] $end
$var wire 1 * rst $end
$var wire 5 3 shamt [4:0] $end
$var wire 5 4 wr_addr [4:0] $end
$var wire 32 5 wr_data [31:0] $end
$var wire 32 6 rd_data2 [31:0] $end
$var wire 32 7 rd_data1 [31:0] $end
$scope module alu $end
$var wire 4 8 funct [3:0] $end
$var wire 5 9 shamt [4:0] $end
$var wire 32 : operand2 [31:0] $end
$var wire 32 ; operand1 [31:0] $end
$var reg 32 < alu_result [31:0] $end
$upscope $end
$scope module rf $end
$var wire 1 % RegWrite $end
$var wire 1 & clk $end
$var wire 5 = rd_addr1 [4:0] $end
$var wire 5 > rd_addr2 [4:0] $end
$var wire 1 * rst $end
$var wire 5 ? wr_addr [4:0] $end
$var wire 32 @ wr_data [31:0] $end
$var reg 32 A rd_data1 [31:0] $end
$var reg 32 B rd_data2 [31:0] $end
$upscope $end
$upscope $end
$scope task Test $end
$var reg 1 C RegWrite_in $end
$var reg 6 D funct_in [5:0] $end
$var reg 5 E rd_addr1_in [4:0] $end
$var reg 5 F rd_addr2_in [4:0] $end
$var reg 32 G rd_data1_in [31:0] $end
$var reg 32 H rd_data2_in [31:0] $end
$var reg 5 I shamt_in [4:0] $end
$var reg 5 J wr_addr_in [4:0] $end
$var reg 32 K wr_data_in [31:0] $end
$upscope $end
$upscope $end
$enddefinitions $end
$comment Show the parameter values. $end
$dumpall
b10011100010000 $
$end
#0
$dumpvars
bx K
bx J
bx I
bx H
bx G
bx F
bx E
bx D
xC
bx B
bx A
bx @
bx ?
bx >
bx =
bx <
bx ;
bx :
bx 9
bx 8
bx 7
bx 6
bx 5
bx 4
bx 3
bx 2
bx 1
bx 0
b0 /
b0 .
b0 -
bx ,
bx +
1*
bx )
bx (
bx '
0&
0%
bx #
bx "
bx !
$end
#5000
1&
#10000
0&
#15000
1&
0*
#20000
0&
#25000
1&
b11110011111110110111101111111110 K
b1110001111100010011100010100000 H
b11000010101110100101001111111110 G
1C
b11 D
b1 I
b11110 J
b1001 F
b10000 E
#26000
b11110011111110110111101111111110 !
b11110011111110110111101111111110 5
b11110011111110110111101111111110 <
b11110011111110110111101111111110 @
b1110001111100010011100010100000 "
b1110001111100010011100010100000 6
b1110001111100010011100010100000 :
b1110001111100010011100010100000 B
b11000010101110100101001111111110 #
b11000010101110100101001111111110 7
b11000010101110100101001111111110 ;
b11000010101110100101001111111110 A
1%
b11 '
b11 0
b11 8
b1 +
b1 3
b1 9
b11110 ,
b11110 4
b11110 ?
b1001 )
b1001 2
b1001 >
b10000 (
b10000 1
b10000 =
#27000
b1 .
#30000
0&
#35000
1&
b1 K
b1101001000010110011010100001100 H
b10010111111011010010110011110 G
b1010 D
b111 F
b11100 E
b1 /
#36000
b1 !
b1 5
b1 <
b1 @
b1101001000010110011010100001100 "
b1101001000010110011010100001100 6
b1101001000010110011010100001100 :
b1101001000010110011010100001100 B
b10010111111011010010110011110 #
b10010111111011010010110011110 7
b10010111111011010010110011110 ;
b10010111111011010010110011110 A
b1010 '
b1010 0
b1010 8
b111 )
b111 2
b111 >
b11100 (
b11100 1
b11100 =
#37000
b10 .
#40000
0&
#45000
1&
b10000010001011000101010000000 K
b10010111111011010010110011110 H
b100011010000110011000000011110 G
0C
b111 D
b10110 I
b1011 J
b11100 F
b1010 E
b10 /
#46000
b10000010001011000101010000000 !
b10000010001011000101010000000 5
b10000010001011000101010000000 <
b10000010001011000101010000000 @
b10010111111011010010110011110 "
b10010111111011010010110011110 6
b10010111111011010010110011110 :
b10010111111011010010110011110 B
b100011010000110011000000011110 #
b100011010000110011000000011110 7
b100011010000110011000000011110 ;
b100011010000110011000000011110 A
0%
b111 '
b111 0
b111 8
b10110 +
b10110 3
b10110 9
b1011 ,
b1011 4
b1011 ?
b11100 )
b11100 2
b11100 >
b1010 (
b1010 1
b1010 =
#47000
b11 .
#50000
0&
#55000
1&
b11101111101110100111010110000000 K
b100011010000110011000000011110 H
b10010111111011010010110011110 G
1C
b10000 I
b1100 J
b1010 F
b11100 E
b11 /
#56000
b11101111101110100111010110000000 !
b11101111101110100111010110000000 5
b11101111101110100111010110000000 <
b11101111101110100111010110000000 @
b100011010000110011000000011110 "
b100011010000110011000000011110 6
b100011010000110011000000011110 :
b100011010000110011000000011110 B
b10010111111011010010110011110 #
b10010111111011010010110011110 7
b10010111111011010010110011110 ;
b10010111111011010010110011110 A
1%
b10000 +
b10000 3
b10000 9
b1100 ,
b1100 4
b1100 ?
b1010 )
b1010 2
b1010 >
b11100 (
b11100 1
b11100 =
#57000
b100 .
#60000
0&
#65000
1&
b1 K
b11101110101101111001000100101100 H
b11111010110111110101100010111010 G
0C
b1100 D
b10100 I
b11100 J
b1111 F
b10010 E
b100 /
#66000
b1 !
b1 5
b1 <
b1 @
b11101110101101111001000100101100 "
b11101110101101111001000100101100 6
b11101110101101111001000100101100 :
b11101110101101111001000100101100 B
b11111010110111110101100010111010 #
b11111010110111110101100010111010 7
b11111010110111110101100010111010 ;
b11111010110111110101100010111010 A
0%
b1100 '
b1100 0
b1100 8
b10100 +
b10100 3
b10100 9
b11100 ,
b11100 4
b11100 ?
b1111 )
b1111 2
b1111 >
b10010 (
b10010 1
b10010 =
#67000
b101 .
#70000
0&
#75000
1&
b1111000000000000000000000000000 K
b10010111111011010010110011110 H
b10000100011101100111010111001 G
1C
b100 D
b11010 I
b10 J
b11100 F
b11011 E
b101 /
#76000
b1111000000000000000000000000000 !
b1111000000000000000000000000000 5
b1111000000000000000000000000000 <
b1111000000000000000000000000000 @
b10010111111011010010110011110 "
b10010111111011010010110011110 6
b10010111111011010010110011110 :
b10010111111011010010110011110 B
b10000100011101100111010111001 #
b10000100011101100111010111001 7
b10000100011101100111010111001 ;
b10000100011101100111010111001 A
1%
b100 '
b100 0
b100 8
b11010 +
b11010 3
b11010 9
b10 ,
b10 4
b10 ?
b11100 )
b11100 2
b11100 >
b11011 (
b11011 1
b11011 =
#77000
b110 .
#80000
0&
#85000
1&
b10001000101010101000 K
b10000110000110011000101111101010 H
b1 D
b1010 J
b11010 F
b110 /
#86000
b10001000101010101000 !
b10001000101010101000 5
b10001000101010101000 <
b10001000101010101000 @
b10000110000110011000101111101010 "
b10000110000110011000101111101010 6
b10000110000110011000101111101010 :
b10000110000110011000101111101010 B
b1 '
b1 0
b1 8
b1010 ,
b1010 4
b1010 ?
b11010 )
b11010 2
b11010 >
#87000
b111 .
#90000
0&
#95000
1&
b1001 K
b10011111000110011010001011011111 H
b11100110010100100111011111010001 G
0C
b110 D
b11100 I
b101 J
b110 F
b10001 E
b111 /
#96000
b1001 !
b1001 5
b1001 <
b1001 @
b10011111000110011010001011011111 "
b10011111000110011010001011011111 6
b10011111000110011010001011011111 :
b10011111000110011010001011011111 B
b11100110010100100111011111010001 #
b11100110010100100111011111010001 7
b11100110010100100111011111010001 ;
b11100110010100100111011111010001 A
0%
b110 '
b110 0
b110 8
b11100 +
b11100 3
b11100 9
b101 ,
b101 4
b101 ?
b110 )
b110 2
b110 >
b10001 (
b10001 1
b10001 =
#97000
b1000 .
#100000
0&
#105000
1&
b1001101001100111111110100011001 K
b10001011010111110000100000001000 H
b11011000100100110000010100100001 G
1C
b111 D
b1 I
b11110 J
b11000 F
b10101 E
b1000 /
#106000
b1001101001100111111110100011001 !
b1001101001100111111110100011001 5
b1001101001100111111110100011001 <
b1001101001100111111110100011001 @
b10001011010111110000100000001000 "
b10001011010111110000100000001000 6
b10001011010111110000100000001000 :
b10001011010111110000100000001000 B
b11011000100100110000010100100001 #
b11011000100100110000010100100001 7
b11011000100100110000010100100001 ;
b11011000100100110000010100100001 A
1%
b111 '
b111 0
b111 8
b1 +
b1 3
b1 9
b11110 ,
b11110 4
b11110 ?
b11000 )
b11000 2
b11000 >
b10101 (
b10101 1
b10101 =
#107000
b1001 .
#110000
0&
#115000
1&
b10010111111111110111110111111 K
b10000100011101100111010111001 H
b10010111111011010010110011110 G
b11 D
b11001 I
b1000 J
b11011 F
b11100 E
b1001 /
#116000
b10010111111111110111110111111 !
b10010111111111110111110111111 5
b10010111111111110111110111111 <
b10010111111111110111110111111 @
b10000100011101100111010111001 "
b10000100011101100111010111001 6
b10000100011101100111010111001 :
b10000100011101100111010111001 B
b10010111111011010010110011110 #
b10010111111011010010110011110 7
b10010111111011010010110011110 ;
b10010111111011010010110011110 A
b11 '
b11 0
b11 8
b11001 +
b11001 3
b11001 9
b1000 ,
b1000 4
b1000 ?
b11011 )
b11011 2
b11011 >
b11100 (
b11100 1
b11100 =
#117000
b1010 .
#120000
0&
#125000
1&
b10000010000100000101011101010001 K
b10001010000100001101111101011011 H
b11100110010100100111011111010001 G
b1 D
b10011 I
b10001 J
b1011 F
b10001 E
b1010 /
#126000
b10000010000100000101011101010001 !
b10000010000100000101011101010001 5
b10000010000100000101011101010001 <
b10000010000100000101011101010001 @
b10001010000100001101111101011011 "
b10001010000100001101111101011011 6
b10001010000100001101111101011011 :
b10001010000100001101111101011011 B
b11100110010100100111011111010001 #
b11100110010100100111011111010001 7
b11100110010100100111011111010001 ;
b11100110010100100111011111010001 A
b1 '
b1 0
b1 8
b10011 +
b10011 3
b10011 9
b10001 ,
b10001 4
b10001 ?
b1011 )
b1011 2
b1011 >
b10001 (
b10001 1
b10001 =
#127000
b1011 .
#130000
0&
#135000
b10000010000100000101011101010001 !
b10000010000100000101011101010001 5
b10000010000100000101011101010001 <
b10000010000100000101011101010001 @
b10000010000100000101011101010001 #
b10000010000100000101011101010001 7
b10000010000100000101011101010001 ;
b10000010000100000101011101010001 A
1&
b1001101111110000001111100000100 K
b1001100100011010111010010100 H
b1000100011010011011000110010000 G
b1000 D
b1 I
b1001 J
b0 F
b10111 E
b1011 /
#136000
b1001101111110000001111100000100 !
b1001101111110000001111100000100 5
b1001101111110000001111100000100 <
b1001101111110000001111100000100 @
b1001100100011010111010010100 "
b1001100100011010111010010100 6
b1001100100011010111010010100 :
b1001100100011010111010010100 B
b1000100011010011011000110010000 #
b1000100011010011011000110010000 7
b1000100011010011011000110010000 ;
b1000100011010011011000110010000 A
b1000 '
b1000 0
b1000 8
b1 +
b1 3
b1 9
b1001 ,
b1001 4
b1001 ?
b0 )
b0 2
b0 >
b10111 (
b10111 1
b10111 =
#137000
b1100 .
#140000
0&
#145000
1&
b10001010000110010110101000000011 K
b10001010000100001101111101011011 H
b10001000101010101000 G
b0 D
b10000 I
b1011 J
b1011 F
b1010 E
b1100 /
#146000
b10001010000110010110101000000011 !
b10001010000110010110101000000011 5
b10001010000110010110101000000011 <
b10001010000110010110101000000011 @
b10001010000100001101111101011011 "
b10001010000100001101111101011011 6
b10001010000100001101111101011011 :
b10001010000100001101111101011011 B
b10001000101010101000 #
b10001000101010101000 7
b10001000101010101000 ;
b10001000101010101000 A
b0 '
b0 0
b0 8
b10000 +
b10000 3
b10000 9
b1011 ,
b1011 4
b1011 ?
b1011 )
b1011 2
b1011 >
b1010 (
b1010 1
b1010 =
#147000
b1101 .
#150000
0&
#155000
b10001010001000011111010010101011 !
b10001010001000011111010010101011 5
b10001010001000011111010010101011 <
b10001010001000011111010010101011 @
b10001010000110010110101000000011 "
b10001010000110010110101000000011 6
b10001010000110010110101000000011 :
b10001010000110010110101000000011 B
1&
b0 K
b1111101001111110111011100101001 H
b10001110000001001011101100011111 G
0C
b1010 D
b11 I
b11111 J
b11101 F
b100 E
b1101 /
#156000
b0 !
b0 5
b0 <
b0 @
b1111101001111110111011100101001 "
b1111101001111110111011100101001 6
b1111101001111110111011100101001 :
b1111101001111110111011100101001 B
b10001110000001001011101100011111 #
b10001110000001001011101100011111 7
b10001110000001001011101100011111 ;
b10001110000001001011101100011111 A
0%
b1010 '
b1010 0
b1010 8
b11 +
b11 3
b11 9
b11111 ,
b11111 4
b11111 ?
b11101 )
b11101 2
b11101 >
b100 (
b100 1
b100 =
#157000
b1110 .
#160000
0&
#165000
1&
b10001110110011101011100100000 K
b10000100011101100111010111001 H
b10010111111011010010110011110 G
1C
b100 D
b101 I
b100 J
b11011 F
b11100 E
b1110 /
#166000
b10001110110011101011100100000 !
b10001110110011101011100100000 5
b10001110110011101011100100000 <
b10001110110011101011100100000 @
b10000100011101100111010111001 "
b10000100011101100111010111001 6
b10000100011101100111010111001 :
b10000100011101100111010111001 B
b10010111111011010010110011110 #
b10010111111011010010110011110 7
b10010111111011010010110011110 ;
b10010111111011010010110011110 A
1%
b100 '
b100 0
b100 8
b101 +
b101 3
b101 9
b100 ,
b100 4
b100 ?
b11011 )
b11011 2
b11011 >
b11100 (
b11100 1
b11100 =
#167000
b1111 .
#170000
0&
#175000
1&
b0 K
b11001010101101011000100100011111 H
b10000110000110011000101111101010 G
b1011 D
b1011 I
b11110 J
b101 F
b11010 E
b1111 /
#176000
b0 !
b0 5
b0 <
b0 @
b11001010101101011000100100011111 "
b11001010101101011000100100011111 6
b11001010101101011000100100011111 :
b11001010101101011000100100011111 B
b10000110000110011000101111101010 #
b10000110000110011000101111101010 7
b10000110000110011000101111101010 ;
b10000110000110011000101111101010 A
b1011 '
b1011 0
b1011 8
b1011 +
b1011 3
b1011 9
b11110 ,
b11110 4
b11110 ?
b101 )
b101 2
b101 >
b11010 (
b11010 1
b11010 =
#177000
b10000 .
#180000
0&
#185000
1&
b1010011111111100000000000000000 K
b11000010101110100101001111111110 H
b10000100011101100111010111001 G
0C
b1101 D
b100 I
b100 J
b10000 F
b11011 E
b10000 /
#186000
b1010011111111100000000000000000 !
b1010011111111100000000000000000 5
b1010011111111100000000000000000 <
b1010011111111100000000000000000 @
b11000010101110100101001111111110 "
b11000010101110100101001111111110 6
b11000010101110100101001111111110 :
b11000010101110100101001111111110 B
b10000100011101100111010111001 #
b10000100011101100111010111001 7
b10000100011101100111010111001 ;
b10000100011101100111010111001 A
0%
b1101 '
b1101 0
b1101 8
b100 +
b100 3
b100 9
b100 ,
b100 4
b100 ?
b10000 )
b10000 2
b10000 >
b11011 (
b11011 1
b11011 =
#187000
b10001 .
#190000
0&
#195000
1&
b1011001111000000000000000000000 K
b10010111111011010010110011110 H
b1001101111110000001111100000100 G
b100 D
b10100 I
b1010 J
b11100 F
b1001 E
b10001 /
#196000
b1011001111000000000000000000000 !
b1011001111000000000000000000000 5
b1011001111000000000000000000000 <
b1011001111000000000000000000000 @
b10010111111011010010110011110 "
b10010111111011010010110011110 6
b10010111111011010010110011110 :
b10010111111011010010110011110 B
b1001101111110000001111100000100 #
b1001101111110000001111100000100 7
b1001101111110000001111100000100 ;
b1001101111110000001111100000100 A
b100 '
b100 0
b100 8
b10100 +
b10100 3
b10100 9
b1010 ,
b1010 4
b1010 ?
b11100 )
b11100 2
b11100 >
b1001 (
b1001 1
b1001 =
#197000
b10010 .
#200000
0&
#205000
1&
b11010010101111101101111111111111 K
b11000010101110100101001111111110 H
b10000100011101100111010111001 G
1C
b11 D
b11011 I
b1111 J
b10000 F
b11011 E
b10010 /
#206000
b11010010101111101101111111111111 !
b11010010101111101101111111111111 5
b11010010101111101101111111111111 <
b11010010101111101101111111111111 @
b11000010101110100101001111111110 "
b11000010101110100101001111111110 6
b11000010101110100101001111111110 :
b11000010101110100101001111111110 B
b10000100011101100111010111001 #
b10000100011101100111010111001 7
b10000100011101100111010111001 ;
b10000100011101100111010111001 A
1%
b11 '
b11 0
b11 8
b11011 +
b11011 3
b11011 9
b1111 ,
b1111 4
b1111 ?
b10000 )
b10000 2
b10000 >
b11011 (
b11011 1
b11011 =
#207000
b10011 .
#210000
0&
#215000
1&
b11110101011011000010110110000010 K
b10111000001001101000000110000000 G
0C
b111 D
b111 I
b1000 J
b11 E
b10011 /
#216000
b11110101011011000010110110000010 !
b11110101011011000010110110000010 5
b11110101011011000010110110000010 <
b11110101011011000010110110000010 @
b10111000001001101000000110000000 #
b10111000001001101000000110000000 7
b10111000001001101000000110000000 ;
b10111000001001101000000110000000 A
0%
b111 '
b111 0
b111 8
b111 +
b111 3
b111 9
b1000 ,
b1000 4
b1000 ?
b11 (
b11 1
b11 =
#217000
b10100 .
#220000
0&
#225000
1&
b11100011010011011010111010111000 K
b11010010101111101101111111111111 H
b10000100011101100111010111001 G
1C
b0 D
b11001 I
b10 J
b1111 F
b11011 E
b10100 /
#226000
b11100011010011011010111010111000 !
b11100011010011011010111010111000 5
b11100011010011011010111010111000 <
b11100011010011011010111010111000 @
b11010010101111101101111111111111 "
b11010010101111101101111111111111 6
b11010010101111101101111111111111 :
b11010010101111101101111111111111 B
b10000100011101100111010111001 #
b10000100011101100111010111001 7
b10000100011101100111010111001 ;
b10000100011101100111010111001 A
1%
b0 '
b0 0
b0 8
b11001 +
b11001 3
b11001 9
b10 ,
b10 4
b10 ?
b1111 )
b1111 2
b1111 >
b11011 (
b11011 1
b11011 =
#227000
b10101 .
#230000
0&
#235000
1&
b1 K
b11011000100100110000010100100001 H
b1111101001111110111011100101001 G
0C
b1010 D
b1 I
b1011 J
b10101 F
b11101 E
b10101 /
#236000
b1 !
b1 5
b1 <
b1 @
b11011000100100110000010100100001 "
b11011000100100110000010100100001 6
b11011000100100110000010100100001 :
b11011000100100110000010100100001 B
b1111101001111110111011100101001 #
b1111101001111110111011100101001 7
b1111101001111110111011100101001 ;
b1111101001111110111011100101001 A
0%
b1010 '
b1010 0
b1010 8
b1 +
b1 3
b1 9
b1011 ,
b1011 4
b1011 ?
b10101 )
b10101 2
b10101 >
b11101 (
b11101 1
b11101 =
#237000
b10110 .
#240000
0&
#245000
1&
b10111000001001101000000 K
b10111000001001101000000110000000 H
b1010011111000100000110000111111 G
b110 D
b1001 I
b11000 J
b11 F
b11111 E
b10110 /
#246000
b10111000001001101000000 !
b10111000001001101000000 5
b10111000001001101000000 <
b10111000001001101000000 @
b10111000001001101000000110000000 "
b10111000001001101000000110000000 6
b10111000001001101000000110000000 :
b10111000001001101000000110000000 B
b1010011111000100000110000111111 #
b1010011111000100000110000111111 7
b1010011111000100000110000111111 ;
b1010011111000100000110000111111 A
b110 '
b110 0
b110 8
b1001 +
b1001 3
b1001 9
b11000 ,
b11000 4
b11000 ?
b11 )
b11 2
b11 >
b11111 (
b11111 1
b11111 =
#247000
b10111 .
#250000
0&
#255000
1&
b10111110001011010000100101011001 K
b10101101100111100011101010100000 H
b10000100011101100111010111001 G
b0 D
b1010 I
b10101 J
b10011 F
b11011 E
b10111 /
#256000
b10111110001011010000100101011001 !
b10111110001011010000100101011001 5
b10111110001011010000100101011001 <
b10111110001011010000100101011001 @
b10101101100111100011101010100000 "
b10101101100111100011101010100000 6
b10101101100111100011101010100000 :
b10101101100111100011101010100000 B
b10000100011101100111010111001 #
b10000100011101100111010111001 7
b10000100011101100111010111001 ;
b10000100011101100111010111001 A
b0 '
b0 0
b0 8
b1010 +
b1010 3
b1010 9
b10101 ,
b10101 4
b10101 ?
b10011 )
b10011 2
b10011 >
b11011 (
b11011 1
b11011 =
#257000
b11000 .
#260000
0&
#265000
1&
b1011000101110100000000000000000 K
b11111010110111110101100010111010 H
b10001011010111110000100000001000 G
1C
b1101 D
b0 I
b11000 J
b10010 F
b11000 E
b11000 /
#266000
b1011000101110100000000000000000 !
b1011000101110100000000000000000 5
b1011000101110100000000000000000 <
b1011000101110100000000000000000 @
b11111010110111110101100010111010 "
b11111010110111110101100010111010 6
b11111010110111110101100010111010 :
b11111010110111110101100010111010 B
b10001011010111110000100000001000 #
b10001011010111110000100000001000 7
b10001011010111110000100000001000 ;
b10001011010111110000100000001000 A
1%
b1101 '
b1101 0
b1101 8
b0 +
b0 3
b0 9
b11000 ,
b11000 4
b11000 ?
b10010 )
b10010 2
b10010 >
b11000 (
b11000 1
b11000 =
#267000
b11001 .
#270000
0&
#275000
b1011000101110100000000000000000 !
b1011000101110100000000000000000 5
b1011000101110100000000000000000 <
b1011000101110100000000000000000 @
b1011000101110100000000000000000 #
b1011000101110100000000000000000 7
b1011000101110100000000000000000 ;
b1011000101110100000000000000000 A
1&
b1 K
b11101001011001010100101110100111 H
b1111101001111110111011100101001 G
b110 D
b11111 I
b11100 J
b10100 F
b11101 E
b11001 /
#276000
b1 !
b1 5
b1 <
b1 @
b11101001011001010100101110100111 "
b11101001011001010100101110100111 6
b11101001011001010100101110100111 :
b11101001011001010100101110100111 B
b1111101001111110111011100101001 #
b1111101001111110111011100101001 7
b1111101001111110111011100101001 ;
b1111101001111110111011100101001 A
b110 '
b110 0
b110 8
b11111 +
b11111 3
b11111 9
b11100 ,
b11100 4
b11100 ?
b10100 )
b10100 2
b10100 >
b11101 (
b11101 1
b11101 =
#277000
b11010 .
#280000
0&
